<?xml version="1.0" encoding="Shift_JIS"?>
<?xml:stylesheet type="text/xsl" href="spreadData.xsl"?>
<!--  
 *******execute SQL*******
select
     prod_class.class_id as クラスID
    ,prod_class.short_name as クラス名ショート
    ,prod_family.family_id as ファミリーID
    ,prod_family.short_name as ファミリー名ショート
    ,product.prod_id as プロダクトID
    ,product.short_name as プロダクト名ショート
from
     prod_class,prod_family,product
where
        prod_class.class_id=prod_family.class_id
    and prod_family.family_id=product.family_id
group by
     prod_class.class_id
    ,prod_class.short_name
    ,prod_family.family_id
    ,prod_family.short_name
    ,product.prod_id
    ,product.short_name
order by
     prod_class.class_id
    ,prod_class.short_name
    ,prod_family.family_id
    ,prod_family.short_name
    ,product.prod_id
    ,product.short_name


Propertyの説明
propertyId:一意に決めるもの
rewrite:trueのものを設定できる（画面に出す）
dispStr:画面に出す文字
setKind:text or list 画面でのテキストボックスかリストか
setName:値が設定してある属性の名前を入れる（ここの設定値から属性の名前を再度求める）
setName→dispRow or line :実際の値が入っているところ
listVal:setKindがListの時にある。SelectBoxの中の項目一覧、ValとNameは:区切り、項目は;区切り
-->
<OpenOLAP>
	<property id="property">
		<dispRow propertyId="1" rewrite="true" dispStr="一度に表示する行数" setKind="text" setName="dispRow" dispRow="50" startRow="1" endRow="5"/>
		<tableLine propertyId="2" rewrite="true" dispStr="セルの結合" setKind="list" setName="line" line="simple" listValKind="fix" listVal="simple:結合しない;union:結合する"/>
		<rowHeader1 propertyId="103" rewrite="true" dispStr="行ヘッダー１" setKind="child" setName="child">
			<rowHeaderCd1 propertyId="3" dispStr="CD" setKind="list" setName="value" value="プロダクトID" listValKind="xmlNode" listVal="//OpenOLAP/sql/sqlcol/@*[name()=&quot;name&quot;]"/>
			<rowHeaderName1 propertyId="13" dispStr="名前" setKind="list" setName="value" value="プロダクト名" listValKind="xmlNode" listVal="//OpenOLAP/sql/sqlcol/@*[name()=&quot;name&quot;]"/>
		</rowHeader1>
		<rowHeader2 propertyId="104" rewrite="true" dispStr="行ヘッダー２" setKind="child" setName="child">
			<rowHeaderCd2 propertyId="4" dispStr="CD" setKind="list" setName="value" value="インダストリーID" listValKind="xmlNode" listVal="//OpenOLAP/sql/sqlcol/@*[name()=&quot;name&quot;]"/>
			<rowHeaderName2 propertyId="14" dispStr="名前" setKind="list" setName="value" value="インダストリー名" listValKind="xmlNode" listVal="//OpenOLAP/sql/sqlcol/@*[name()=&quot;name&quot;]"/>
		</rowHeader2>
		<rowHeader3 propertyId="105" rewrite="true" dispStr="行ヘッダー３" setKind="child" setName="child">
			<rowHeaderCd3 propertyId="5" dispStr="CD" setKind="list" setName="value" value="" listValKind="xmlNode" listVal="//OpenOLAP/sql/sqlcol/@*[name()=&quot;name&quot;]"/>
			<rowHeaderName3 propertyId="15" dispStr="名前" setKind="list" setName="value" value="" listValKind="xmlNode" listVal="//OpenOLAP/sql/sqlcol/@*[name()=&quot;name&quot;]"/>
		</rowHeader3>
		<colHeader1 propertyId="106" rewrite="true" dispStr="列ヘッダー１" setKind="child" setName="child">
			<colHeaderCd1 propertyId="6" dispStr="CD" setKind="list" setName="value" value="チャネルID" listValKind="xmlNode" listVal="//OpenOLAP/sql/sqlcol/@*[name()=&quot;name&quot;]"/>
			<colHeaderName1 propertyId="16" dispStr="名前" setKind="list" setName="value" value="チャネル名" listValKind="xmlNode" listVal="//OpenOLAP/sql/sqlcol/@*[name()=&quot;name&quot;]"/>
		</colHeader1>
		<colHeader2 propertyId="106" rewrite="true" dispStr="列ヘッダー２" setKind="child" setName="child">
			<colHeaderCd2 propertyId="7" dispStr="CD" setKind="list" setName="value" value="" listValKind="xmlNode" listVal="//OpenOLAP/sql/sqlcol/@*[name()=&quot;name&quot;]"/>
			<colHeaderName2 propertyId="17" dispStr="名前" setKind="list" setName="value" value="" listValKind="xmlNode" listVal="//OpenOLAP/sql/sqlcol/@*[name()=&quot;name&quot;]"/>
		</colHeader2>
		<colHeader3 propertyId="106" rewrite="true" dispStr="列ヘッダー３" setKind="child" setName="child">
			<colHeaderCd3 propertyId="8" dispStr="CD" setKind="list" setName="value" value="" listValKind="xmlNode" listVal="//OpenOLAP/sql/sqlcol/@*[name()=&quot;name&quot;]"/>
			<colHeaderName3 propertyId="18" dispStr="名前" setKind="list" setName="value" value="" listValKind="xmlNode" listVal="//OpenOLAP/sql/sqlcol/@*[name()=&quot;name&quot;]"/>
		</colHeader3>
		<pattern row="simple" frm="table" xslfile="2"/>
		<measures propertyId="106" rewrite="true" dispStr="メジャー" setKind="child" setName="child">
			<measure1 propertyId="201" dispStr="" setKind="list" setName="value" value="売上" listValKind="xmlNode" listVal="//OpenOLAP/sql/sqlcol/@*[name()=&quot;name&quot;]"/>
			<measure2 propertyId="202" dispStr="" setKind="list" setName="value" value="" listValKind="xmlNode" listVal="//OpenOLAP/sql/sqlcol/@*[name()=&quot;name&quot;]"/>
			<measure3 propertyId="203" dispStr="" setKind="list" setName="value" value="" listValKind="xmlNode" listVal="//OpenOLAP/sql/sqlcol/@*[name()=&quot;name&quot;]"/>
			<measure4 propertyId="204" dispStr="" setKind="list" setName="value" value="" listValKind="xmlNode" listVal="//OpenOLAP/sql/sqlcol/@*[name()=&quot;name&quot;]"/>
			<measure5 propertyId="205" dispStr="" setKind="list" setName="value" value="" listValKind="xmlNode" listVal="//OpenOLAP/sql/sqlcol/@*[name()=&quot;name&quot;]"/>
			<measure6 propertyId="206" dispStr="" setKind="list" setName="value" value="" listValKind="xmlNode" listVal="//OpenOLAP/sql/sqlcol/@*[name()=&quot;name&quot;]"/>
			<measure7 propertyId="207" dispStr="" setKind="list" setName="value" value="" listValKind="xmlNode" listVal="//OpenOLAP/sql/sqlcol/@*[name()=&quot;name&quot;]"/>
			<measure8 propertyId="208" dispStr="" setKind="list" setName="value" value="" listValKind="xmlNode" listVal="//OpenOLAP/sql/sqlcol/@*[name()=&quot;name&quot;]"/>
			<measure9 propertyId="209" dispStr="" setKind="list" setName="value" value="" listValKind="xmlNode" listVal="//OpenOLAP/sql/sqlcol/@*[name()=&quot;name&quot;]"/>
			<measure10 propertyId="210" dispStr="" setKind="list" setName="value" value="" listValKind="xmlNode" listVal="//OpenOLAP/sql/sqlcol/@*[name()=&quot;name&quot;]"/>
		</measures>
	</property>
	<sql id="sql">
		<sqlcol id="1" name="チャネルID" datatype="string" cellformat="str" dbId="channel_1"/><sqlcol id="2" name="チャネル名" datatype="string" cellformat="str" dbId="channel_2"/><sqlcol id="3" name="プロダクトID" datatype="string" cellformat="str" dbId="product_1"/><sqlcol id="4" name="プロダクト名" datatype="string" cellformat="str" dbId="product_2"/><sqlcol id="5" name="売上" datatype="string" cellformat="str" dbId="fact_sales_1"/><sqlcol id="6" name="インダストリーID" datatype="string" cellformat="str" dbId="geog_industry_1"/><sqlcol id="7" name="インダストリー名" datatype="string" cellformat="str" dbId="geog_industry_2"/></sql>
	<screenSql id="screenSql">
		<where_clause id="fact_sales_2" dbId="fact_sales_2" name="time"/></screenSql>
	<additionalData>
		<rowHeader>
			<row 表題1="データ1" 表題2="データ" 表題3="100"></row>
			<row 表題1="データ2" 表題2="データ" 表題3="200"></row>
		</rowHeader>
		<colHeader>
			<row 表題1="データ1" 表題2="データ" 表題3="100"></row>
		</colHeader>
	</additionalData><data><row チャネルID="CC2" チャネル名="直販" プロダクトID="PP11" プロダクト名="Envoy ｽﾀﾝﾀﾞｰﾄﾞ" 売上="492475" インダストリーID="GG113" インダストリー名="製造"/><row チャネルID="CC2" チャネル名="直販" プロダクトID="PP11" プロダクト名="Envoy ｽﾀﾝﾀﾞｰﾄﾞ" 売上="156132" インダストリーID="GG114" インダストリー名="機械"/><row チャネルID="CC2" チャネル名="直販" プロダクトID="PP11" プロダクト名="Envoy ｽﾀﾝﾀﾞｰﾄﾞ" 売上="421344" インダストリーID="GG115" インダストリー名="防衛"/><row チャネルID="CC2" チャネル名="直販" プロダクトID="PP11" プロダクト名="Envoy ｽﾀﾝﾀﾞｰﾄﾞ" 売上="741488" インダストリーID="GG116" インダストリー名="コンサルティング"/><row チャネルID="CC2" チャネル名="直販" プロダクトID="PP11" プロダクト名="Envoy ｽﾀﾝﾀﾞｰﾄﾞ" 売上="888375" インダストリーID="GG117" インダストリー名="ＳＩ"/><row チャネルID="CC2" チャネル名="直販" プロダクトID="PP11" プロダクト名="Envoy ｽﾀﾝﾀﾞｰﾄﾞ" 売上="181506" インダストリーID="GG118" インダストリー名="航空宇宙"/><row チャネルID="CC2" チャネル名="直販" プロダクトID="PP11" プロダクト名="Envoy ｽﾀﾝﾀﾞｰﾄﾞ" 売上="672570" インダストリーID="GG119" インダストリー名="転売"/><row チャネルID="CC2" チャネル名="直販" プロダクトID="PP11" プロダクト名="Envoy ｽﾀﾝﾀﾞｰﾄﾞ" 売上="146917" インダストリーID="GG120" インダストリー名="政府"/><row チャネルID="CC2" チャネル名="直販" プロダクトID="PP11" プロダクト名="Envoy ｽﾀﾝﾀﾞｰﾄﾞ" 売上="8378" インダストリーID="GG121" インダストリー名="教育"/><row チャネルID="CC2" チャネル名="直販" プロダクトID="PP12" プロダクト名="Envoy ｴｸﾞｾﾞｸﾃｨﾌﾞ" 売上="78431" インダストリーID="GG113" インダストリー名="製造"/><row チャネルID="CC2" チャネル名="直販" プロダクトID="PP12" プロダクト名="Envoy ｴｸﾞｾﾞｸﾃｨﾌﾞ" 売上="33208" インダストリーID="GG114" インダストリー名="機械"/><row チャネルID="CC2" チャネル名="直販" プロダクトID="PP12" プロダクト名="Envoy ｴｸﾞｾﾞｸﾃｨﾌﾞ" 売上="83331" インダストリーID="GG115" インダストリー名="防衛"/><row チャネルID="CC2" チャネル名="直販" プロダクトID="PP12" プロダクト名="Envoy ｴｸﾞｾﾞｸﾃｨﾌﾞ" 売上="137047" インダストリーID="GG116" インダストリー名="コンサルティング"/><row チャネルID="CC2" チャネル名="直販" プロダクトID="PP12" プロダクト名="Envoy ｴｸﾞｾﾞｸﾃｨﾌﾞ" 売上="134733" インダストリーID="GG117" インダストリー名="ＳＩ"/><row チャネルID="CC2" チャネル名="直販" プロダクトID="PP12" プロダクト名="Envoy ｴｸﾞｾﾞｸﾃｨﾌﾞ" 売上="29897" インダストリーID="GG118" インダストリー名="航空宇宙"/><row チャネルID="CC2" チャネル名="直販" プロダクトID="PP12" プロダクト名="Envoy ｴｸﾞｾﾞｸﾃｨﾌﾞ" 売上="111922" インダストリーID="GG119" インダストリー名="転売"/><row チャネルID="CC2" チャネル名="直販" プロダクトID="PP12" プロダクト名="Envoy ｴｸﾞｾﾞｸﾃｨﾌﾞ" 売上="24791" インダストリーID="GG120" インダストリー名="政府"/><row チャネルID="CC2" チャネル名="直販" プロダクトID="PP12" プロダクト名="Envoy ｴｸﾞｾﾞｸﾃｨﾌﾞ" 売上="1018" インダストリーID="GG121" インダストリー名="教育"/><row チャネルID="CC2" チャネル名="直販" プロダクトID="PP13" プロダクト名="Envoy ｱﾝﾊﾞｻﾀﾞｰ" 売上="84657" インダストリーID="GG113" インダストリー名="製造"/><row チャネルID="CC2" チャネル名="直販" プロダクトID="PP13" プロダクト名="Envoy ｱﾝﾊﾞｻﾀﾞｰ" 売上="41332" インダストリーID="GG114" インダストリー名="機械"/><row チャネルID="CC2" チャネル名="直販" プロダクトID="PP13" プロダクト名="Envoy ｱﾝﾊﾞｻﾀﾞｰ" 売上="74095" インダストリーID="GG115" インダストリー名="防衛"/><row チャネルID="CC2" チャネル名="直販" プロダクトID="PP13" プロダクト名="Envoy ｱﾝﾊﾞｻﾀﾞｰ" 売上="150685" インダストリーID="GG116" インダストリー名="コンサルティング"/><row チャネルID="CC2" チャネル名="直販" プロダクトID="PP13" プロダクト名="Envoy ｱﾝﾊﾞｻﾀﾞｰ" 売上="150226" インダストリーID="GG117" インダストリー名="ＳＩ"/><row チャネルID="CC2" チャネル名="直販" プロダクトID="PP13" プロダクト名="Envoy ｱﾝﾊﾞｻﾀﾞｰ" 売上="36266" インダストリーID="GG118" インダストリー名="航空宇宙"/><row チャネルID="CC2" チャネル名="直販" プロダクトID="PP13" プロダクト名="Envoy ｱﾝﾊﾞｻﾀﾞｰ" 売上="118592" インダストリーID="GG119" インダストリー名="転売"/><row チャネルID="CC2" チャネル名="直販" プロダクトID="PP13" プロダクト名="Envoy ｱﾝﾊﾞｻﾀﾞｰ" 売上="25115" インダストリーID="GG120" インダストリー名="政府"/><row チャネルID="CC2" チャネル名="直販" プロダクトID="PP13" プロダクト名="Envoy ｱﾝﾊﾞｻﾀﾞｰ" 売上="1296" インダストリーID="GG121" インダストリー名="教育"/><row チャネルID="CC2" チャネル名="直販" プロダクトID="PP14" プロダクト名="Sentinel ｽﾀﾝﾀﾞｰﾄﾞ" 売上="287732" インダストリーID="GG113" インダストリー名="製造"/><row チャネルID="CC2" チャネル名="直販" プロダクトID="PP14" プロダクト名="Sentinel ｽﾀﾝﾀﾞｰﾄﾞ" 売上="139937" インダストリーID="GG114" インダストリー名="機械"/><row チャネルID="CC2" チャネル名="直販" プロダクトID="PP14" プロダクト名="Sentinel ｽﾀﾝﾀﾞｰﾄﾞ" 売上="257651" インダストリーID="GG115" インダストリー名="防衛"/><row チャネルID="CC2" チャネル名="直販" プロダクトID="PP14" プロダクト名="Sentinel ｽﾀﾝﾀﾞｰﾄﾞ" 売上="497037" インダストリーID="GG116" インダストリー名="コンサルティング"/><row チャネルID="CC2" チャネル名="直販" プロダクトID="PP14" プロダクト名="Sentinel ｽﾀﾝﾀﾞｰﾄﾞ" 売上="523875" インダストリーID="GG117" インダストリー名="ＳＩ"/><row チャネルID="CC2" チャネル名="直販" プロダクトID="PP14" プロダクト名="Sentinel ｽﾀﾝﾀﾞｰﾄﾞ" 売上="125267" インダストリーID="GG118" インダストリー名="航空宇宙"/><row チャネルID="CC2" チャネル名="直販" プロダクトID="PP14" プロダクト名="Sentinel ｽﾀﾝﾀﾞｰﾄﾞ" 売上="432804" インダストリーID="GG119" インダストリー名="転売"/><row チャネルID="CC2" チャネル名="直販" プロダクトID="PP14" プロダクト名="Sentinel ｽﾀﾝﾀﾞｰﾄﾞ" 売上="83598" インダストリーID="GG120" インダストリー名="政府"/><row チャネルID="CC2" チャネル名="直販" プロダクトID="PP14" プロダクト名="Sentinel ｽﾀﾝﾀﾞｰﾄﾞ" 売上="5527" インダストリーID="GG121" インダストリー名="教育"/><row チャネルID="CC2" チャネル名="直販" プロダクトID="PP15" プロダクト名="Sentinel ﾌｧｲﾅﾝｼｬﾙ" 売上="81478" インダストリーID="GG113" インダストリー名="製造"/><row チャネルID="CC2" チャネル名="直販" プロダクトID="PP15" プロダクト名="Sentinel ﾌｧｲﾅﾝｼｬﾙ" 売上="31992" インダストリーID="GG114" インダストリー名="機械"/><row チャネルID="CC2" チャネル名="直販" プロダクトID="PP15" プロダクト名="Sentinel ﾌｧｲﾅﾝｼｬﾙ" 売上="68407" インダストリーID="GG115" インダストリー名="防衛"/><row チャネルID="CC2" チャネル名="直販" プロダクトID="PP15" プロダクト名="Sentinel ﾌｧｲﾅﾝｼｬﾙ" 売上="130755" インダストリーID="GG116" インダストリー名="コンサルティング"/><row チャネルID="CC2" チャネル名="直販" プロダクトID="PP15" プロダクト名="Sentinel ﾌｧｲﾅﾝｼｬﾙ" 売上="161406" インダストリーID="GG117" インダストリー名="ＳＩ"/><row チャネルID="CC2" チャネル名="直販" プロダクトID="PP15" プロダクト名="Sentinel ﾌｧｲﾅﾝｼｬﾙ" 売上="48665" インダストリーID="GG118" インダストリー名="航空宇宙"/><row チャネルID="CC2" チャネル名="直販" プロダクトID="PP15" プロダクト名="Sentinel ﾌｧｲﾅﾝｼｬﾙ" 売上="125693" インダストリーID="GG119" インダストリー名="転売"/><row チャネルID="CC2" チャネル名="直販" プロダクトID="PP15" プロダクト名="Sentinel ﾌｧｲﾅﾝｼｬﾙ" 売上="25393" インダストリーID="GG120" インダストリー名="政府"/><row チャネルID="CC2" チャネル名="直販" プロダクトID="PP15" プロダクト名="Sentinel ﾌｧｲﾅﾝｼｬﾙ" 売上="950" インダストリーID="GG121" インダストリー名="教育"/><row チャネルID="CC2" チャネル名="直販" プロダクトID="PP16" プロダクト名="Sentinel ﾏﾙﾁﾒﾃﾞｨｱ" 売上="265657" インダストリーID="GG113" インダストリー名="製造"/><row チャネルID="CC2" チャネル名="直販" プロダクトID="PP16" プロダクト名="Sentinel ﾏﾙﾁﾒﾃﾞｨｱ" 売上="101581" インダストリーID="GG114" インダストリー名="機械"/><row チャネルID="CC2" チャネル名="直販" プロダクトID="PP16" プロダクト名="Sentinel ﾏﾙﾁﾒﾃﾞｨｱ" 売上="270352" インダストリーID="GG115" インダストリー名="防衛"/><row チャネルID="CC2" チャネル名="直販" プロダクトID="PP16" プロダクト名="Sentinel ﾏﾙﾁﾒﾃﾞｨｱ" 売上="476714" インダストリーID="GG116" インダストリー名="コンサルティング"/><row チャネルID="CC2" チャネル名="直販" プロダクトID="PP16" プロダクト名="Sentinel ﾏﾙﾁﾒﾃﾞｨｱ" 売上="478265" インダストリーID="GG117" インダストリー名="ＳＩ"/><row チャネルID="CC2" チャネル名="直販" プロダクトID="PP16" プロダクト名="Sentinel ﾏﾙﾁﾒﾃﾞｨｱ" 売上="92892" インダストリーID="GG118" インダストリー名="航空宇宙"/><row チャネルID="CC2" チャネル名="直販" プロダクトID="PP16" プロダクト名="Sentinel ﾏﾙﾁﾒﾃﾞｨｱ" 売上="362696" インダストリーID="GG119" インダストリー名="転売"/><row チャネルID="CC2" チャネル名="直販" プロダクトID="PP16" プロダクト名="Sentinel ﾏﾙﾁﾒﾃﾞｨｱ" 売上="70142" インダストリーID="GG120" インダストリー名="政府"/><row チャネルID="CC2" チャネル名="直販" プロダクトID="PP16" プロダクト名="Sentinel ﾏﾙﾁﾒﾃﾞｨｱ" 売上="3436" インダストリーID="GG121" インダストリー名="教育"/><row チャネルID="CC2" チャネル名="直販" プロダクトID="PP17" プロダクト名="ＯＳﾄﾞｷｭﾒﾝﾄ一式" 売上="5311" インダストリーID="GG113" インダストリー名="製造"/><row チャネルID="CC2" チャネル名="直販" プロダクトID="PP17" プロダクト名="ＯＳﾄﾞｷｭﾒﾝﾄ一式" 売上="1614" インダストリーID="GG114" インダストリー名="機械"/><row チャネルID="CC2" チャネル名="直販" プロダクトID="PP17" プロダクト名="ＯＳﾄﾞｷｭﾒﾝﾄ一式" 売上="5124" インダストリーID="GG115" インダストリー名="防衛"/><row チャネルID="CC2" チャネル名="直販" プロダクトID="PP17" プロダクト名="ＯＳﾄﾞｷｭﾒﾝﾄ一式" 売上="8319" インダストリーID="GG116" インダストリー名="コンサルティング"/><row チャネルID="CC2" チャネル名="直販" プロダクトID="PP17" プロダクト名="ＯＳﾄﾞｷｭﾒﾝﾄ一式" 売上="8771" インダストリーID="GG117" インダストリー名="ＳＩ"/><row チャネルID="CC2" チャネル名="直販" プロダクトID="PP17" プロダクト名="ＯＳﾄﾞｷｭﾒﾝﾄ一式" 売上="2049" インダストリーID="GG118" インダストリー名="航空宇宙"/><row チャネルID="CC2" チャネル名="直販" プロダクトID="PP17" プロダクト名="ＯＳﾄﾞｷｭﾒﾝﾄ一式" 売上="5804" インダストリーID="GG119" インダストリー名="転売"/><row チャネルID="CC2" チャネル名="直販" プロダクトID="PP17" プロダクト名="ＯＳﾄﾞｷｭﾒﾝﾄ一式" 売上="1400" インダストリーID="GG120" インダストリー名="政府"/><row チャネルID="CC2" チャネル名="直販" プロダクトID="PP17" プロダクト名="ＯＳﾄﾞｷｭﾒﾝﾄ一式" 売上="75" インダストリーID="GG121" インダストリー名="教育"/><row チャネルID="CC2" チャネル名="直販" プロダクトID="PP18" プロダクト名="ﾉｰﾄPC ｷｬﾘﾝｸﾞ･ｹｰｽ" 売上="5975" インダストリーID="GG113" インダストリー名="製造"/><row チャネルID="CC2" チャネル名="直販" プロダクトID="PP18" プロダクト名="ﾉｰﾄPC ｷｬﾘﾝｸﾞ･ｹｰｽ" 売上="2143" インダストリーID="GG114" インダストリー名="機械"/><row チャネルID="CC2" チャネル名="直販" プロダクトID="PP18" プロダクト名="ﾉｰﾄPC ｷｬﾘﾝｸﾞ･ｹｰｽ" 売上="5995" インダストリーID="GG115" インダストリー名="防衛"/><row チャネルID="CC2" チャネル名="直販" プロダクトID="PP18" プロダクト名="ﾉｰﾄPC ｷｬﾘﾝｸﾞ･ｹｰｽ" 売上="11191" インダストリーID="GG116" インダストリー名="コンサルティング"/><row チャネルID="CC2" チャネル名="直販" プロダクトID="PP18" プロダクト名="ﾉｰﾄPC ｷｬﾘﾝｸﾞ･ｹｰｽ" 売上="12658" インダストリーID="GG117" インダストリー名="ＳＩ"/><row チャネルID="CC2" チャネル名="直販" プロダクトID="PP18" プロダクト名="ﾉｰﾄPC ｷｬﾘﾝｸﾞ･ｹｰｽ" 売上="3099" インダストリーID="GG118" インダストリー名="航空宇宙"/><row チャネルID="CC2" チャネル名="直販" プロダクトID="PP18" プロダクト名="ﾉｰﾄPC ｷｬﾘﾝｸﾞ･ｹｰｽ" 売上="8555" インダストリーID="GG119" インダストリー名="転売"/><row チャネルID="CC2" チャネル名="直販" プロダクトID="PP18" プロダクト名="ﾉｰﾄPC ｷｬﾘﾝｸﾞ･ｹｰｽ" 売上="1803" インダストリーID="GG120" インダストリー名="政府"/><row チャネルID="CC2" チャネル名="直販" プロダクトID="PP18" プロダクト名="ﾉｰﾄPC ｷｬﾘﾝｸﾞ･ｹｰｽ" 売上="74" インダストリーID="GG121" インダストリー名="教育"/><row チャネルID="CC2" チャネル名="直販" プロダクトID="PP19" プロダクト名="ﾓﾆﾀｰ 15 Super VGA" 売上="25620" インダストリーID="GG113" インダストリー名="製造"/><row チャネルID="CC2" チャネル名="直販" プロダクトID="PP19" プロダクト名="ﾓﾆﾀｰ 15 Super VGA" 売上="9092" インダストリーID="GG114" インダストリー名="機械"/><row チャネルID="CC2" チャネル名="直販" プロダクトID="PP19" プロダクト名="ﾓﾆﾀｰ 15 Super VGA" 売上="25918" インダストリーID="GG115" インダストリー名="防衛"/><row チャネルID="CC2" チャネル名="直販" プロダクトID="PP19" プロダクト名="ﾓﾆﾀｰ 15 Super VGA" 売上="41874" インダストリーID="GG116" インダストリー名="コンサルティング"/><row チャネルID="CC2" チャネル名="直販" プロダクトID="PP19" プロダクト名="ﾓﾆﾀｰ 15 Super VGA" 売上="39858" インダストリーID="GG117" インダストリー名="ＳＩ"/><row チャネルID="CC2" チャネル名="直販" プロダクトID="PP19" プロダクト名="ﾓﾆﾀｰ 15 Super VGA" 売上="11681" インダストリーID="GG118" インダストリー名="航空宇宙"/><row チャネルID="CC2" チャネル名="直販" プロダクトID="PP19" プロダクト名="ﾓﾆﾀｰ 15 Super VGA" 売上="29132" インダストリーID="GG119" インダストリー名="転売"/><row チャネルID="CC2" チャネル名="直販" プロダクトID="PP19" プロダクト名="ﾓﾆﾀｰ 15 Super VGA" 売上="7855" インダストリーID="GG120" インダストリー名="政府"/><row チャネルID="CC2" チャネル名="直販" プロダクトID="PP19" プロダクト名="ﾓﾆﾀｰ 15 Super VGA" 売上="302" インダストリーID="GG121" インダストリー名="教育"/><row チャネルID="CC2" チャネル名="直販" プロダクトID="PP20" プロダクト名="ﾓﾆﾀｰ 19 Super VGA" 売上="18452" インダストリーID="GG113" インダストリー名="製造"/><row チャネルID="CC2" チャネル名="直販" プロダクトID="PP20" プロダクト名="ﾓﾆﾀｰ 19 Super VGA" 売上="7911" インダストリーID="GG114" インダストリー名="機械"/><row チャネルID="CC2" チャネル名="直販" プロダクトID="PP20" プロダクト名="ﾓﾆﾀｰ 19 Super VGA" 売上="20388" インダストリーID="GG115" インダストリー名="防衛"/><row チャネルID="CC2" チャネル名="直販" プロダクトID="PP20" プロダクト名="ﾓﾆﾀｰ 19 Super VGA" 売上="32315" インダストリーID="GG116" インダストリー名="コンサルティング"/><row チャネルID="CC2" チャネル名="直販" プロダクトID="PP20" プロダクト名="ﾓﾆﾀｰ 19 Super VGA" 売上="33303" インダストリーID="GG117" インダストリー名="ＳＩ"/><row チャネルID="CC2" チャネル名="直販" プロダクトID="PP20" プロダクト名="ﾓﾆﾀｰ 19 Super VGA" 売上="9617" インダストリーID="GG118" インダストリー名="航空宇宙"/><row チャネルID="CC2" チャネル名="直販" プロダクトID="PP20" プロダクト名="ﾓﾆﾀｰ 19 Super VGA" 売上="25758" インダストリーID="GG119" インダストリー名="転売"/><row チャネルID="CC2" チャネル名="直販" プロダクトID="PP20" プロダクト名="ﾓﾆﾀｰ 19 Super VGA" 売上="5352" インダストリーID="GG120" インダストリー名="政府"/><row チャネルID="CC2" チャネル名="直販" プロダクトID="PP20" プロダクト名="ﾓﾆﾀｰ 19 Super VGA" 売上="236" インダストリーID="GG121" インダストリー名="教育"/><row チャネルID="CC2" チャネル名="直販" プロダクトID="PP21" プロダクト名="Envoy 内蔵キーボード" 売上="11208" インダストリーID="GG113" インダストリー名="製造"/><row チャネルID="CC2" チャネル名="直販" プロダクトID="PP21" プロダクト名="Envoy 内蔵キーボード" 売上="4756" インダストリーID="GG114" インダストリー名="機械"/><row チャネルID="CC2" チャネル名="直販" プロダクトID="PP21" プロダクト名="Envoy 内蔵キーボード" 売上="13231" インダストリーID="GG115" インダストリー名="防衛"/><row チャネルID="CC2" チャネル名="直販" プロダクトID="PP21" プロダクト名="Envoy 内蔵キーボード" 売上="21651" インダストリーID="GG116" インダストリー名="コンサルティング"/><row チャネルID="CC2" チャネル名="直販" プロダクトID="PP21" プロダクト名="Envoy 内蔵キーボード" 売上="21154" インダストリーID="GG117" インダストリー名="ＳＩ"/><row チャネルID="CC2" チャネル名="直販" プロダクトID="PP21" プロダクト名="Envoy 内蔵キーボード" 売上="5860" インダストリーID="GG118" インダストリー名="航空宇宙"/><row チャネルID="CC2" チャネル名="直販" プロダクトID="PP21" プロダクト名="Envoy 内蔵キーボード" 売上="15610" インダストリーID="GG119" インダストリー名="転売"/><row チャネルID="CC2" チャネル名="直販" プロダクトID="PP21" プロダクト名="Envoy 内蔵キーボード" 売上="3929" インダストリーID="GG120" インダストリー名="政府"/><row チャネルID="CC2" チャネル名="直販" プロダクトID="PP21" プロダクト名="Envoy 内蔵キーボード" 売上="203" インダストリーID="GG121" インダストリー名="教育"/><row チャネルID="CC2" チャネル名="直販" プロダクトID="PP22" プロダクト名="外付け 101キーボード" 売上="9632" インダストリーID="GG113" インダストリー名="製造"/><row チャネルID="CC2" チャネル名="直販" プロダクトID="PP22" プロダクト名="外付け 101キーボード" 売上="3073" インダストリーID="GG114" インダストリー名="機械"/><row チャネルID="CC2" チャネル名="直販" プロダクトID="PP22" プロダクト名="外付け 101キーボード" 売上="9160" インダストリーID="GG115" インダストリー名="防衛"/><row チャネルID="CC2" チャネル名="直販" プロダクトID="PP22" プロダクト名="外付け 101キーボード" 売上="14119" インダストリーID="GG116" インダストリー名="コンサルティング"/><row チャネルID="CC2" チャネル名="直販" プロダクトID="PP22" プロダクト名="外付け 101キーボード" 売上="19372" インダストリーID="GG117" インダストリー名="ＳＩ"/><row チャネルID="CC2" チャネル名="直販" プロダクトID="PP22" プロダクト名="外付け 101キーボード" 売上="4153" インダストリーID="GG118" インダストリー名="航空宇宙"/><row チャネルID="CC2" チャネル名="直販" プロダクトID="PP22" プロダクト名="外付け 101キーボード" 売上="13013" インダストリーID="GG119" インダストリー名="転売"/><row チャネルID="CC2" チャネル名="直販" プロダクトID="PP22" プロダクト名="外付け 101キーボード" 売上="3050" インダストリーID="GG120" インダストリー名="政府"/><row チャネルID="CC2" チャネル名="直販" プロダクトID="PP22" プロダクト名="外付け 101キーボード" 売上="159" インダストリーID="GG121" インダストリー名="教育"/><row チャネルID="CC2" チャネル名="直販" プロダクトID="PP23" プロダクト名="PCMCIA ﾓﾃﾞﾑ/FAX 28800bps" 売上="44938" インダストリーID="GG113" インダストリー名="製造"/><row チャネルID="CC2" チャネル名="直販" プロダクトID="PP23" プロダクト名="PCMCIA ﾓﾃﾞﾑ/FAX 28800bps" 売上="18377" インダストリーID="GG114" インダストリー名="機械"/><row チャネルID="CC2" チャネル名="直販" プロダクトID="PP23" プロダクト名="PCMCIA ﾓﾃﾞﾑ/FAX 28800bps" 売上="38259" インダストリーID="GG115" インダストリー名="防衛"/><row チャネルID="CC2" チャネル名="直販" プロダクトID="PP23" プロダクト名="PCMCIA ﾓﾃﾞﾑ/FAX 28800bps" 売上="74197" インダストリーID="GG116" インダストリー名="コンサルティング"/><row チャネルID="CC2" チャネル名="直販" プロダクトID="PP23" プロダクト名="PCMCIA ﾓﾃﾞﾑ/FAX 28800bps" 売上="89907" インダストリーID="GG117" インダストリー名="ＳＩ"/><row チャネルID="CC2" チャネル名="直販" プロダクトID="PP23" プロダクト名="PCMCIA ﾓﾃﾞﾑ/FAX 28800bps" 売上="19281" インダストリーID="GG118" インダストリー名="航空宇宙"/><row チャネルID="CC2" チャネル名="直販" プロダクトID="PP23" プロダクト名="PCMCIA ﾓﾃﾞﾑ/FAX 28800bps" 売上="63427" インダストリーID="GG119" インダストリー名="転売"/><row チャネルID="CC2" チャネル名="直販" プロダクトID="PP23" プロダクト名="PCMCIA ﾓﾃﾞﾑ/FAX 28800bps" 売上="12706" インダストリーID="GG120" インダストリー名="政府"/><row チャネルID="CC2" チャネル名="直販" プロダクトID="PP23" プロダクト名="PCMCIA ﾓﾃﾞﾑ/FAX 28800bps" 売上="554" インダストリーID="GG121" インダストリー名="教育"/><row チャネルID="CC2" チャネル名="直販" プロダクトID="PP24" プロダクト名="SIMM- 8MB PCMCIAIIｶｰﾄﾞ" 売上="32735" インダストリーID="GG113" インダストリー名="製造"/><row チャネルID="CC2" チャネル名="直販" プロダクトID="PP24" プロダクト名="SIMM- 8MB PCMCIAIIｶｰﾄﾞ" 売上="11223" インダストリーID="GG114" インダストリー名="機械"/><row チャネルID="CC2" チャネル名="直販" プロダクトID="PP24" プロダクト名="SIMM- 8MB PCMCIAIIｶｰﾄﾞ" 売上="28625" インダストリーID="GG115" インダストリー名="防衛"/><row チャネルID="CC2" チャネル名="直販" プロダクトID="PP24" プロダクト名="SIMM- 8MB PCMCIAIIｶｰﾄﾞ" 売上="51091" インダストリーID="GG116" インダストリー名="コンサルティング"/><row チャネルID="CC2" チャネル名="直販" プロダクトID="PP24" プロダクト名="SIMM- 8MB PCMCIAIIｶｰﾄﾞ" 売上="56766" インダストリーID="GG117" インダストリー名="ＳＩ"/><row チャネルID="CC2" チャネル名="直販" プロダクトID="PP24" プロダクト名="SIMM- 8MB PCMCIAIIｶｰﾄﾞ" 売上="16252" インダストリーID="GG118" インダストリー名="航空宇宙"/><row チャネルID="CC2" チャネル名="直販" プロダクトID="PP24" プロダクト名="SIMM- 8MB PCMCIAIIｶｰﾄﾞ" 売上="39691" インダストリーID="GG119" インダストリー名="転売"/><row チャネルID="CC2" チャネル名="直販" プロダクトID="PP24" プロダクト名="SIMM- 8MB PCMCIAIIｶｰﾄﾞ" 売上="9258" インダストリーID="GG120" インダストリー名="政府"/><row チャネルID="CC2" チャネル名="直販" プロダクトID="PP24" プロダクト名="SIMM- 8MB PCMCIAIIｶｰﾄﾞ" 売上="375" インダストリーID="GG121" インダストリー名="教育"/><row チャネルID="CC2" チャネル名="直販" プロダクトID="PP25" プロダクト名="SIMM- 16MB PCMCIAIIｶｰﾄﾞ" 売上="17120" インダストリーID="GG113" インダストリー名="製造"/><row チャネルID="CC2" チャネル名="直販" プロダクトID="PP25" プロダクト名="SIMM- 16MB PCMCIAIIｶｰﾄﾞ" 売上="6731" インダストリーID="GG114" インダストリー名="機械"/><row チャネルID="CC2" チャネル名="直販" プロダクトID="PP25" プロダクト名="SIMM- 16MB PCMCIAIIｶｰﾄﾞ" 売上="15143" インダストリーID="GG115" インダストリー名="防衛"/><row チャネルID="CC2" チャネル名="直販" プロダクトID="PP25" プロダクト名="SIMM- 16MB PCMCIAIIｶｰﾄﾞ" 売上="29396" インダストリーID="GG116" インダストリー名="コンサルティング"/><row チャネルID="CC2" チャネル名="直販" プロダクトID="PP25" プロダクト名="SIMM- 16MB PCMCIAIIｶｰﾄﾞ" 売上="31979" インダストリーID="GG117" インダストリー名="ＳＩ"/><row チャネルID="CC2" チャネル名="直販" プロダクトID="PP25" プロダクト名="SIMM- 16MB PCMCIAIIｶｰﾄﾞ" 売上="7914" インダストリーID="GG118" インダストリー名="航空宇宙"/><row チャネルID="CC2" チャネル名="直販" プロダクトID="PP25" プロダクト名="SIMM- 16MB PCMCIAIIｶｰﾄﾞ" 売上="24376" インダストリーID="GG119" インダストリー名="転売"/><row チャネルID="CC2" チャネル名="直販" プロダクトID="PP25" プロダクト名="SIMM- 16MB PCMCIAIIｶｰﾄﾞ" 売上="5015" インダストリーID="GG120" インダストリー名="政府"/><row チャネルID="CC2" チャネル名="直販" プロダクトID="PP25" プロダクト名="SIMM- 16MB PCMCIAIIｶｰﾄﾞ" 売上="239" インダストリーID="GG121" インダストリー名="教育"/><row チャネルID="CC2" チャネル名="直販" プロダクトID="PP26" プロダクト名="ﾏﾙﾁﾒﾃﾞｨｱ･ｽﾋﾟｰｶ" 売上="5009" インダストリーID="GG113" インダストリー名="製造"/><row チャネルID="CC2" チャネル名="直販" プロダクトID="PP26" プロダクト名="ﾏﾙﾁﾒﾃﾞｨｱ･ｽﾋﾟｰｶ" 売上="2086" インダストリーID="GG114" インダストリー名="機械"/><row チャネルID="CC2" チャネル名="直販" プロダクトID="PP26" プロダクト名="ﾏﾙﾁﾒﾃﾞｨｱ･ｽﾋﾟｰｶ" 売上="5420" インダストリーID="GG115" インダストリー名="防衛"/><row チャネルID="CC2" チャネル名="直販" プロダクトID="PP26" プロダクト名="ﾏﾙﾁﾒﾃﾞｨｱ･ｽﾋﾟｰｶ" 売上="8868" インダストリーID="GG116" インダストリー名="コンサルティング"/><row チャネルID="CC2" チャネル名="直販" プロダクトID="PP26" プロダクト名="ﾏﾙﾁﾒﾃﾞｨｱ･ｽﾋﾟｰｶ" 売上="8876" インダストリーID="GG117" インダストリー名="ＳＩ"/><row チャネルID="CC2" チャネル名="直販" プロダクトID="PP26" プロダクト名="ﾏﾙﾁﾒﾃﾞｨｱ･ｽﾋﾟｰｶ" 売上="1947" インダストリーID="GG118" インダストリー名="航空宇宙"/><row チャネルID="CC2" チャネル名="直販" プロダクトID="PP26" プロダクト名="ﾏﾙﾁﾒﾃﾞｨｱ･ｽﾋﾟｰｶ" 売上="7318" インダストリーID="GG119" インダストリー名="転売"/><row チャネルID="CC2" チャネル名="直販" プロダクトID="PP26" プロダクト名="ﾏﾙﾁﾒﾃﾞｨｱ･ｽﾋﾟｰｶ" 売上="1610" インダストリーID="GG120" インダストリー名="政府"/><row チャネルID="CC2" チャネル名="直販" プロダクトID="PP26" プロダクト名="ﾏﾙﾁﾒﾃﾞｨｱ･ｽﾋﾟｰｶ" 売上="61" インダストリーID="GG121" インダストリー名="教育"/><row チャネルID="CC2" チャネル名="直販" プロダクトID="PP27" プロダクト名="Unix/Windows 1ﾕｰｻﾞ･ﾊﾟｯｸ" 売上="24688" インダストリーID="GG113" インダストリー名="製造"/><row チャネルID="CC2" チャネル名="直販" プロダクトID="PP27" プロダクト名="Unix/Windows 1ﾕｰｻﾞ･ﾊﾟｯｸ" 売上="10270" インダストリーID="GG114" インダストリー名="機械"/><row チャネルID="CC2" チャネル名="直販" プロダクトID="PP27" プロダクト名="Unix/Windows 1ﾕｰｻﾞ･ﾊﾟｯｸ" 売上="27901" インダストリーID="GG115" インダストリー名="防衛"/><row チャネルID="CC2" チャネル名="直販" プロダクトID="PP27" プロダクト名="Unix/Windows 1ﾕｰｻﾞ･ﾊﾟｯｸ" 売上="48185" インダストリーID="GG116" インダストリー名="コンサルティング"/><row チャネルID="CC2" チャネル名="直販" プロダクトID="PP27" プロダクト名="Unix/Windows 1ﾕｰｻﾞ･ﾊﾟｯｸ" 売上="60750" インダストリーID="GG117" インダストリー名="ＳＩ"/><row チャネルID="CC2" チャネル名="直販" プロダクトID="PP27" プロダクト名="Unix/Windows 1ﾕｰｻﾞ･ﾊﾟｯｸ" 売上="11619" インダストリーID="GG118" インダストリー名="航空宇宙"/><row チャネルID="CC2" チャネル名="直販" プロダクトID="PP27" プロダクト名="Unix/Windows 1ﾕｰｻﾞ･ﾊﾟｯｸ" 売上="38355" インダストリーID="GG119" インダストリー名="転売"/><row チャネルID="CC2" チャネル名="直販" プロダクトID="PP27" プロダクト名="Unix/Windows 1ﾕｰｻﾞ･ﾊﾟｯｸ" 売上="8069" インダストリーID="GG120" インダストリー名="政府"/><row チャネルID="CC2" チャネル名="直販" プロダクトID="PP27" プロダクト名="Unix/Windows 1ﾕｰｻﾞ･ﾊﾟｯｸ" 売上="421" インダストリーID="GG121" インダストリー名="教育"/><row チャネルID="CC2" チャネル名="直販" プロダクトID="PP28" プロダクト名="Unix/Windows 5ﾕｰｻﾞ･ﾊﾟｯｸ" 売上="1931" インダストリーID="GG113" インダストリー名="製造"/><row チャネルID="CC2" チャネル名="直販" プロダクトID="PP28" プロダクト名="Unix/Windows 5ﾕｰｻﾞ･ﾊﾟｯｸ" 売上="821" インダストリーID="GG114" インダストリー名="機械"/><row チャネルID="CC2" チャネル名="直販" プロダクトID="PP28" プロダクト名="Unix/Windows 5ﾕｰｻﾞ･ﾊﾟｯｸ" 売上="2059" インダストリーID="GG115" インダストリー名="防衛"/><row チャネルID="CC2" チャネル名="直販" プロダクトID="PP28" プロダクト名="Unix/Windows 5ﾕｰｻﾞ･ﾊﾟｯｸ" 売上="3199" インダストリーID="GG116" インダストリー名="コンサルティング"/><row チャネルID="CC2" チャネル名="直販" プロダクトID="PP28" プロダクト名="Unix/Windows 5ﾕｰｻﾞ･ﾊﾟｯｸ" 売上="3589" インダストリーID="GG117" インダストリー名="ＳＩ"/><row チャネルID="CC2" チャネル名="直販" プロダクトID="PP28" プロダクト名="Unix/Windows 5ﾕｰｻﾞ･ﾊﾟｯｸ" 売上="810" インダストリーID="GG118" インダストリー名="航空宇宙"/><row チャネルID="CC2" チャネル名="直販" プロダクトID="PP28" プロダクト名="Unix/Windows 5ﾕｰｻﾞ･ﾊﾟｯｸ" 売上="2910" インダストリーID="GG119" インダストリー名="転売"/><row チャネルID="CC2" チャネル名="直販" プロダクトID="PP28" プロダクト名="Unix/Windows 5ﾕｰｻﾞ･ﾊﾟｯｸ" 売上="854" インダストリーID="GG120" インダストリー名="政府"/><row チャネルID="CC2" チャネル名="直販" プロダクトID="PP28" プロダクト名="Unix/Windows 5ﾕｰｻﾞ･ﾊﾟｯｸ" 売上="0" インダストリーID="GG121" インダストリー名="教育"/><row チャネルID="CC2" チャネル名="直販" プロダクトID="PP29" プロダクト名="マウス・パッド" 売上="254" インダストリーID="GG113" インダストリー名="製造"/><row チャネルID="CC2" チャネル名="直販" プロダクトID="PP29" プロダクト名="マウス・パッド" 売上="134" インダストリーID="GG114" インダストリー名="機械"/><row チャネルID="CC2" チャネル名="直販" プロダクトID="PP29" プロダクト名="マウス・パッド" 売上="334" インダストリーID="GG115" インダストリー名="防衛"/><row チャネルID="CC2" チャネル名="直販" プロダクトID="PP29" プロダクト名="マウス・パッド" 売上="557" インダストリーID="GG116" インダストリー名="コンサルティング"/><row チャネルID="CC2" チャネル名="直販" プロダクトID="PP29" プロダクト名="マウス・パッド" 売上="569" インダストリーID="GG117" インダストリー名="ＳＩ"/><row チャネルID="CC2" チャネル名="直販" プロダクトID="PP29" プロダクト名="マウス・パッド" 売上="127" インダストリーID="GG118" インダストリー名="航空宇宙"/><row チャネルID="CC2" チャネル名="直販" プロダクトID="PP29" プロダクト名="マウス・パッド" 売上="384" インダストリーID="GG119" インダストリー名="転売"/><row チャネルID="CC2" チャネル名="直販" プロダクトID="PP29" プロダクト名="マウス・パッド" 売上="92" インダストリーID="GG120" インダストリー名="政府"/><row チャネルID="CC2" チャネル名="直販" プロダクトID="PP29" プロダクト名="マウス・パッド" 売上="5" インダストリーID="GG121" インダストリー名="教育"/><row チャネルID="CC2" チャネル名="直販" プロダクトID="PP30" プロダクト名="2.88MB  3.5 FD" 売上="19913" インダストリーID="GG113" インダストリー名="製造"/><row チャネルID="CC2" チャネル名="直販" プロダクトID="PP30" プロダクト名="2.88MB  3.5 FD" 売上="8630" インダストリーID="GG114" インダストリー名="機械"/><row チャネルID="CC2" チャネル名="直販" プロダクトID="PP30" プロダクト名="2.88MB  3.5 FD" 売上="19620" インダストリーID="GG115" インダストリー名="防衛"/><row チャネルID="CC2" チャネル名="直販" プロダクトID="PP30" プロダクト名="2.88MB  3.5 FD" 売上="45770" インダストリーID="GG116" インダストリー名="コンサルティング"/><row チャネルID="CC2" チャネル名="直販" プロダクトID="PP30" プロダクト名="2.88MB  3.5 FD" 売上="46380" インダストリーID="GG117" インダストリー名="ＳＩ"/><row チャネルID="CC2" チャネル名="直販" プロダクトID="PP30" プロダクト名="2.88MB  3.5 FD" 売上="9334" インダストリーID="GG118" インダストリー名="航空宇宙"/><row チャネルID="CC2" チャネル名="直販" プロダクトID="PP30" プロダクト名="2.88MB  3.5 FD" 売上="31189" インダストリーID="GG119" インダストリー名="転売"/><row チャネルID="CC2" チャネル名="直販" プロダクトID="PP30" プロダクト名="2.88MB  3.5 FD" 売上="6956" インダストリーID="GG120" インダストリー名="政府"/><row チャネルID="CC2" チャネル名="直販" プロダクトID="PP30" プロダクト名="2.88MB  3.5 FD" 売上="340" インダストリーID="GG121" インダストリー名="教育"/><row チャネルID="CC2" チャネル名="直販" プロダクトID="PP31" プロダクト名="ﾏﾙﾁﾒﾃﾞｨｱ･ｽﾋﾟｰｶ" 売上="4348" インダストリーID="GG113" インダストリー名="製造"/><row チャネルID="CC2" チャネル名="直販" プロダクトID="PP31" プロダクト名="ﾏﾙﾁﾒﾃﾞｨｱ･ｽﾋﾟｰｶ" 売上="1945" インダストリーID="GG114" インダストリー名="機械"/><row チャネルID="CC2" チャネル名="直販" プロダクトID="PP31" プロダクト名="ﾏﾙﾁﾒﾃﾞｨｱ･ｽﾋﾟｰｶ" 売上="5573" インダストリーID="GG115" インダストリー名="防衛"/><row チャネルID="CC2" チャネル名="直販" プロダクトID="PP31" プロダクト名="ﾏﾙﾁﾒﾃﾞｨｱ･ｽﾋﾟｰｶ" 売上="8466" インダストリーID="GG116" インダストリー名="コンサルティング"/><row チャネルID="CC2" チャネル名="直販" プロダクトID="PP31" プロダクト名="ﾏﾙﾁﾒﾃﾞｨｱ･ｽﾋﾟｰｶ" 売上="9822" インダストリーID="GG117" インダストリー名="ＳＩ"/><row チャネルID="CC2" チャネル名="直販" プロダクトID="PP31" プロダクト名="ﾏﾙﾁﾒﾃﾞｨｱ･ｽﾋﾟｰｶ" 売上="2654" インダストリーID="GG118" インダストリー名="航空宇宙"/><row チャネルID="CC2" チャネル名="直販" プロダクトID="PP31" プロダクト名="ﾏﾙﾁﾒﾃﾞｨｱ･ｽﾋﾟｰｶ" 売上="6430" インダストリーID="GG119" インダストリー名="転売"/><row チャネルID="CC2" チャネル名="直販" プロダクトID="PP31" プロダクト名="ﾏﾙﾁﾒﾃﾞｨｱ･ｽﾋﾟｰｶ" 売上="1443" インダストリーID="GG120" インダストリー名="政府"/><row チャネルID="CC2" チャネル名="直販" プロダクトID="PP31" プロダクト名="ﾏﾙﾁﾒﾃﾞｨｱ･ｽﾋﾟｰｶ" 売上="88" インダストリーID="GG121" インダストリー名="教育"/><row チャネルID="CC2" チャネル名="直販" プロダクトID="PP32" プロダクト名="PCMCIA ﾓﾃﾞﾑ/FAX 19200bps" 売上="3760" インダストリーID="GG113" インダストリー名="製造"/><row チャネルID="CC2" チャネル名="直販" プロダクトID="PP32" プロダクト名="PCMCIA ﾓﾃﾞﾑ/FAX 19200bps" 売上="1437" インダストリーID="GG114" インダストリー名="機械"/><row チャネルID="CC2" チャネル名="直販" プロダクトID="PP32" プロダクト名="PCMCIA ﾓﾃﾞﾑ/FAX 19200bps" 売上="4174" インダストリーID="GG115" インダストリー名="防衛"/><row チャネルID="CC2" チャネル名="直販" プロダクトID="PP32" プロダクト名="PCMCIA ﾓﾃﾞﾑ/FAX 19200bps" 売上="6219" インダストリーID="GG116" インダストリー名="コンサルティング"/><row チャネルID="CC2" チャネル名="直販" プロダクトID="PP32" プロダクト名="PCMCIA ﾓﾃﾞﾑ/FAX 19200bps" 売上="7122" インダストリーID="GG117" インダストリー名="ＳＩ"/><row チャネルID="CC2" チャネル名="直販" プロダクトID="PP32" プロダクト名="PCMCIA ﾓﾃﾞﾑ/FAX 19200bps" 売上="1918" インダストリーID="GG118" インダストリー名="航空宇宙"/><row チャネルID="CC2" チャネル名="直販" プロダクトID="PP32" プロダクト名="PCMCIA ﾓﾃﾞﾑ/FAX 19200bps" 売上="5189" インダストリーID="GG119" インダストリー名="転売"/><row チャネルID="CC2" チャネル名="直販" プロダクトID="PP32" プロダクト名="PCMCIA ﾓﾃﾞﾑ/FAX 19200bps" 売上="1272" インダストリーID="GG120" インダストリー名="政府"/><row チャネルID="CC2" チャネル名="直販" プロダクトID="PP32" プロダクト名="PCMCIA ﾓﾃﾞﾑ/FAX 19200bps" 売上="81" インダストリーID="GG121" インダストリー名="教育"/><row チャネルID="CC3" チャネル名="卸売" プロダクトID="PP11" プロダクト名="Envoy ｽﾀﾝﾀﾞｰﾄﾞ" 売上="797620" インダストリーID="GG113" インダストリー名="製造"/><row チャネルID="CC3" チャネル名="卸売" プロダクトID="PP11" プロダクト名="Envoy ｽﾀﾝﾀﾞｰﾄﾞ" 売上="274475" インダストリーID="GG114" インダストリー名="機械"/><row チャネルID="CC3" チャネル名="卸売" プロダクトID="PP11" プロダクト名="Envoy ｽﾀﾝﾀﾞｰﾄﾞ" 売上="908614" インダストリーID="GG115" インダストリー名="防衛"/><row チャネルID="CC3" チャネル名="卸売" プロダクトID="PP11" プロダクト名="Envoy ｽﾀﾝﾀﾞｰﾄﾞ" 売上="1260082" インダストリーID="GG116" インダストリー名="コンサルティング"/><row チャネルID="CC3" チャネル名="卸売" プロダクトID="PP11" プロダクト名="Envoy ｽﾀﾝﾀﾞｰﾄﾞ" 売上="1323257" インダストリーID="GG117" インダストリー名="ＳＩ"/><row チャネルID="CC3" チャネル名="卸売" プロダクトID="PP11" プロダクト名="Envoy ｽﾀﾝﾀﾞｰﾄﾞ" 売上="373667" インダストリーID="GG118" インダストリー名="航空宇宙"/><row チャネルID="CC3" チャネル名="卸売" プロダクトID="PP11" プロダクト名="Envoy ｽﾀﾝﾀﾞｰﾄﾞ" 売上="1055319" インダストリーID="GG119" インダストリー名="転売"/><row チャネルID="CC3" チャネル名="卸売" プロダクトID="PP11" プロダクト名="Envoy ｽﾀﾝﾀﾞｰﾄﾞ" 売上="229625" インダストリーID="GG120" インダストリー名="政府"/><row チャネルID="CC3" チャネル名="卸売" プロダクトID="PP11" プロダクト名="Envoy ｽﾀﾝﾀﾞｰﾄﾞ" 売上="12315" インダストリーID="GG121" インダストリー名="教育"/><row チャネルID="CC3" チャネル名="卸売" プロダクトID="PP12" プロダクト名="Envoy ｴｸﾞｾﾞｸﾃｨﾌﾞ" 売上="141633" インダストリーID="GG113" インダストリー名="製造"/><row チャネルID="CC3" チャネル名="卸売" プロダクトID="PP12" プロダクト名="Envoy ｴｸﾞｾﾞｸﾃｨﾌﾞ" 売上="51908" インダストリーID="GG114" インダストリー名="機械"/><row チャネルID="CC3" チャネル名="卸売" プロダクトID="PP12" プロダクト名="Envoy ｴｸﾞｾﾞｸﾃｨﾌﾞ" 売上="138626" インダストリーID="GG115" インダストリー名="防衛"/><row チャネルID="CC3" チャネル名="卸売" プロダクトID="PP12" プロダクト名="Envoy ｴｸﾞｾﾞｸﾃｨﾌﾞ" 売上="220945" インダストリーID="GG116" インダストリー名="コンサルティング"/><row チャネルID="CC3" チャネル名="卸売" プロダクトID="PP12" プロダクト名="Envoy ｴｸﾞｾﾞｸﾃｨﾌﾞ" 売上="215023" インダストリーID="GG117" インダストリー名="ＳＩ"/><row チャネルID="CC3" チャネル名="卸売" プロダクトID="PP12" プロダクト名="Envoy ｴｸﾞｾﾞｸﾃｨﾌﾞ" 売上="55686" インダストリーID="GG118" インダストリー名="航空宇宙"/><row チャネルID="CC3" チャネル名="卸売" プロダクトID="PP12" プロダクト名="Envoy ｴｸﾞｾﾞｸﾃｨﾌﾞ" 売上="183201" インダストリーID="GG119" インダストリー名="転売"/><row チャネルID="CC3" チャネル名="卸売" プロダクトID="PP12" プロダクト名="Envoy ｴｸﾞｾﾞｸﾃｨﾌﾞ" 売上="36883" インダストリーID="GG120" インダストリー名="政府"/><row チャネルID="CC3" チャネル名="卸売" プロダクトID="PP12" プロダクト名="Envoy ｴｸﾞｾﾞｸﾃｨﾌﾞ" 売上="1241" インダストリーID="GG121" インダストリー名="教育"/><row チャネルID="CC3" チャネル名="卸売" プロダクトID="PP13" プロダクト名="Envoy ｱﾝﾊﾞｻﾀﾞｰ" 売上="150422" インダストリーID="GG113" インダストリー名="製造"/><row チャネルID="CC3" チャネル名="卸売" プロダクトID="PP13" プロダクト名="Envoy ｱﾝﾊﾞｻﾀﾞｰ" 売上="61347" インダストリーID="GG114" インダストリー名="機械"/><row チャネルID="CC3" チャネル名="卸売" プロダクトID="PP13" プロダクト名="Envoy ｱﾝﾊﾞｻﾀﾞｰ" 売上="141886" インダストリーID="GG115" インダストリー名="防衛"/><row チャネルID="CC3" チャネル名="卸売" プロダクトID="PP13" プロダクト名="Envoy ｱﾝﾊﾞｻﾀﾞｰ" 売上="249142" インダストリーID="GG116" インダストリー名="コンサルティング"/><row チャネルID="CC3" チャネル名="卸売" プロダクトID="PP13" プロダクト名="Envoy ｱﾝﾊﾞｻﾀﾞｰ" 売上="253569" インダストリーID="GG117" インダストリー名="ＳＩ"/><row チャネルID="CC3" チャネル名="卸売" プロダクトID="PP13" プロダクト名="Envoy ｱﾝﾊﾞｻﾀﾞｰ" 売上="66864" インダストリーID="GG118" インダストリー名="航空宇宙"/><row チャネルID="CC3" チャネル名="卸売" プロダクトID="PP13" プロダクト名="Envoy ｱﾝﾊﾞｻﾀﾞｰ" 売上="195989" インダストリーID="GG119" インダストリー名="転売"/><row チャネルID="CC3" チャネル名="卸売" プロダクトID="PP13" プロダクト名="Envoy ｱﾝﾊﾞｻﾀﾞｰ" 売上="40351" インダストリーID="GG120" インダストリー名="政府"/><row チャネルID="CC3" チャネル名="卸売" プロダクトID="PP13" プロダクト名="Envoy ｱﾝﾊﾞｻﾀﾞｰ" 売上="1588" インダストリーID="GG121" インダストリー名="教育"/><row チャネルID="CC3" チャネル名="卸売" プロダクトID="PP14" プロダクト名="Sentinel ｽﾀﾝﾀﾞｰﾄﾞ" 売上="475074" インダストリーID="GG113" インダストリー名="製造"/><row チャネルID="CC3" チャネル名="卸売" プロダクトID="PP14" プロダクト名="Sentinel ｽﾀﾝﾀﾞｰﾄﾞ" 売上="211476" インダストリーID="GG114" インダストリー名="機械"/><row チャネルID="CC3" チャネル名="卸売" プロダクトID="PP14" プロダクト名="Sentinel ｽﾀﾝﾀﾞｰﾄﾞ" 売上="524188" インダストリーID="GG115" インダストリー名="防衛"/><row チャネルID="CC3" チャネル名="卸売" プロダクトID="PP14" プロダクト名="Sentinel ｽﾀﾝﾀﾞｰﾄﾞ" 売上="785898" インダストリーID="GG116" インダストリー名="コンサルティング"/><row チャネルID="CC3" チャネル名="卸売" プロダクトID="PP14" プロダクト名="Sentinel ｽﾀﾝﾀﾞｰﾄﾞ" 売上="873383" インダストリーID="GG117" インダストリー名="ＳＩ"/><row チャネルID="CC3" チャネル名="卸売" プロダクトID="PP14" プロダクト名="Sentinel ｽﾀﾝﾀﾞｰﾄﾞ" 売上="214948" インダストリーID="GG118" インダストリー名="航空宇宙"/><row チャネルID="CC3" チャネル名="卸売" プロダクトID="PP14" プロダクト名="Sentinel ｽﾀﾝﾀﾞｰﾄﾞ" 売上="724691" インダストリーID="GG119" インダストリー名="転売"/><row チャネルID="CC3" チャネル名="卸売" プロダクトID="PP14" プロダクト名="Sentinel ｽﾀﾝﾀﾞｰﾄﾞ" 売上="127045" インダストリーID="GG120" インダストリー名="政府"/><row チャネルID="CC3" チャネル名="卸売" プロダクトID="PP14" プロダクト名="Sentinel ｽﾀﾝﾀﾞｰﾄﾞ" 売上="8257" インダストリーID="GG121" インダストリー名="教育"/><row チャネルID="CC3" チャネル名="卸売" プロダクトID="PP15" プロダクト名="Sentinel ﾌｧｲﾅﾝｼｬﾙ" 売上="146207" インダストリーID="GG113" インダストリー名="製造"/><row チャネルID="CC3" チャネル名="卸売" プロダクトID="PP15" プロダクト名="Sentinel ﾌｧｲﾅﾝｼｬﾙ" 売上="50714" インダストリーID="GG114" インダストリー名="機械"/><row チャネルID="CC3" チャネル名="卸売" プロダクトID="PP15" プロダクト名="Sentinel ﾌｧｲﾅﾝｼｬﾙ" 売上="131206" インダストリーID="GG115" インダストリー名="防衛"/><row チャネルID="CC3" チャネル名="卸売" プロダクトID="PP15" プロダクト名="Sentinel ﾌｧｲﾅﾝｼｬﾙ" 売上="232046" インダストリーID="GG116" インダストリー名="コンサルティング"/><row チャネルID="CC3" チャネル名="卸売" プロダクトID="PP15" プロダクト名="Sentinel ﾌｧｲﾅﾝｼｬﾙ" 売上="236289" インダストリーID="GG117" インダストリー名="ＳＩ"/><row チャネルID="CC3" チャネル名="卸売" プロダクトID="PP15" プロダクト名="Sentinel ﾌｧｲﾅﾝｼｬﾙ" 売上="76900" インダストリーID="GG118" インダストリー名="航空宇宙"/><row チャネルID="CC3" チャネル名="卸売" プロダクトID="PP15" プロダクト名="Sentinel ﾌｧｲﾅﾝｼｬﾙ" 売上="203135" インダストリーID="GG119" インダストリー名="転売"/><row チャネルID="CC3" チャネル名="卸売" プロダクトID="PP15" プロダクト名="Sentinel ﾌｧｲﾅﾝｼｬﾙ" 売上="42641" インダストリーID="GG120" インダストリー名="政府"/><row チャネルID="CC3" チャネル名="卸売" プロダクトID="PP15" プロダクト名="Sentinel ﾌｧｲﾅﾝｼｬﾙ" 売上="2273" インダストリーID="GG121" インダストリー名="教育"/><row チャネルID="CC3" チャネル名="卸売" プロダクトID="PP16" プロダクト名="Sentinel ﾏﾙﾁﾒﾃﾞｨｱ" 売上="434279" インダストリーID="GG113" インダストリー名="製造"/><row チャネルID="CC3" チャネル名="卸売" プロダクトID="PP16" プロダクト名="Sentinel ﾏﾙﾁﾒﾃﾞｨｱ" 売上="160092" インダストリーID="GG114" インダストリー名="機械"/><row チャネルID="CC3" チャネル名="卸売" プロダクトID="PP16" プロダクト名="Sentinel ﾏﾙﾁﾒﾃﾞｨｱ" 売上="508481" インダストリーID="GG115" インダストリー名="防衛"/><row チャネルID="CC3" チャネル名="卸売" プロダクトID="PP16" プロダクト名="Sentinel ﾏﾙﾁﾒﾃﾞｨｱ" 売上="721142" インダストリーID="GG116" インダストリー名="コンサルティング"/><row チャネルID="CC3" チャネル名="卸売" プロダクトID="PP16" プロダクト名="Sentinel ﾏﾙﾁﾒﾃﾞｨｱ" 売上="754868" インダストリーID="GG117" インダストリー名="ＳＩ"/><row チャネルID="CC3" チャネル名="卸売" プロダクトID="PP16" プロダクト名="Sentinel ﾏﾙﾁﾒﾃﾞｨｱ" 売上="188799" インダストリーID="GG118" インダストリー名="航空宇宙"/><row チャネルID="CC3" チャネル名="卸売" プロダクトID="PP16" プロダクト名="Sentinel ﾏﾙﾁﾒﾃﾞｨｱ" 売上="647740" インダストリーID="GG119" インダストリー名="転売"/><row チャネルID="CC3" チャネル名="卸売" プロダクトID="PP16" プロダクト名="Sentinel ﾏﾙﾁﾒﾃﾞｨｱ" 売上="113937" インダストリーID="GG120" インダストリー名="政府"/><row チャネルID="CC3" チャネル名="卸売" プロダクトID="PP16" プロダクト名="Sentinel ﾏﾙﾁﾒﾃﾞｨｱ" 売上="5670" インダストリーID="GG121" インダストリー名="教育"/><row チャネルID="CC3" チャネル名="卸売" プロダクトID="PP17" プロダクト名="ＯＳﾄﾞｷｭﾒﾝﾄ一式" 売上="8452" インダストリーID="GG113" インダストリー名="製造"/><row チャネルID="CC3" チャネル名="卸売" プロダクトID="PP17" プロダクト名="ＯＳﾄﾞｷｭﾒﾝﾄ一式" 売上="3189" インダストリーID="GG114" インダストリー名="機械"/><row チャネルID="CC3" チャネル名="卸売" プロダクトID="PP17" プロダクト名="ＯＳﾄﾞｷｭﾒﾝﾄ一式" 売上="9557" インダストリーID="GG115" インダストリー名="防衛"/><row チャネルID="CC3" チャネル名="卸売" プロダクトID="PP17" プロダクト名="ＯＳﾄﾞｷｭﾒﾝﾄ一式" 売上="13198" インダストリーID="GG116" インダストリー名="コンサルティング"/><row チャネルID="CC3" チャネル名="卸売" プロダクトID="PP17" プロダクト名="ＯＳﾄﾞｷｭﾒﾝﾄ一式" 売上="13686" インダストリーID="GG117" インダストリー名="ＳＩ"/><row チャネルID="CC3" チャネル名="卸売" プロダクトID="PP17" プロダクト名="ＯＳﾄﾞｷｭﾒﾝﾄ一式" 売上="3724" インダストリーID="GG118" インダストリー名="航空宇宙"/><row チャネルID="CC3" チャネル名="卸売" プロダクトID="PP17" プロダクト名="ＯＳﾄﾞｷｭﾒﾝﾄ一式" 売上="10182" インダストリーID="GG119" インダストリー名="転売"/><row チャネルID="CC3" チャネル名="卸売" プロダクトID="PP17" プロダクト名="ＯＳﾄﾞｷｭﾒﾝﾄ一式" 売上="2216" インダストリーID="GG120" インダストリー名="政府"/><row チャネルID="CC3" チャネル名="卸売" プロダクトID="PP17" プロダクト名="ＯＳﾄﾞｷｭﾒﾝﾄ一式" 売上="136" インダストリーID="GG121" インダストリー名="教育"/><row チャネルID="CC3" チャネル名="卸売" プロダクトID="PP18" プロダクト名="ﾉｰﾄPC ｷｬﾘﾝｸﾞ･ｹｰｽ" 売上="10038" インダストリーID="GG113" インダストリー名="製造"/><row チャネルID="CC3" チャネル名="卸売" プロダクトID="PP18" プロダクト名="ﾉｰﾄPC ｷｬﾘﾝｸﾞ･ｹｰｽ" 売上="3520" インダストリーID="GG114" インダストリー名="機械"/><row チャネルID="CC3" チャネル名="卸売" プロダクトID="PP18" プロダクト名="ﾉｰﾄPC ｷｬﾘﾝｸﾞ･ｹｰｽ" 売上="10524" インダストリーID="GG115" インダストリー名="防衛"/><row チャネルID="CC3" チャネル名="卸売" プロダクトID="PP18" プロダクト名="ﾉｰﾄPC ｷｬﾘﾝｸﾞ･ｹｰｽ" 売上="16626" インダストリーID="GG116" インダストリー名="コンサルティング"/><row チャネルID="CC3" チャネル名="卸売" プロダクトID="PP18" プロダクト名="ﾉｰﾄPC ｷｬﾘﾝｸﾞ･ｹｰｽ" 売上="18080" インダストリーID="GG117" インダストリー名="ＳＩ"/><row チャネルID="CC3" チャネル名="卸売" プロダクトID="PP18" プロダクト名="ﾉｰﾄPC ｷｬﾘﾝｸﾞ･ｹｰｽ" 売上="4928" インダストリーID="GG118" インダストリー名="航空宇宙"/><row チャネルID="CC3" チャネル名="卸売" プロダクトID="PP18" プロダクト名="ﾉｰﾄPC ｷｬﾘﾝｸﾞ･ｹｰｽ" 売上="12740" インダストリーID="GG119" インダストリー名="転売"/><row チャネルID="CC3" チャネル名="卸売" プロダクトID="PP18" プロダクト名="ﾉｰﾄPC ｷｬﾘﾝｸﾞ･ｹｰｽ" 売上="2715" インダストリーID="GG120" インダストリー名="政府"/><row チャネルID="CC3" チャネル名="卸売" プロダクトID="PP18" プロダクト名="ﾉｰﾄPC ｷｬﾘﾝｸﾞ･ｹｰｽ" 売上="149" インダストリーID="GG121" インダストリー名="教育"/><row チャネルID="CC3" チャネル名="卸売" プロダクトID="PP19" プロダクト名="ﾓﾆﾀｰ 15 Super VGA" 売上="42870" インダストリーID="GG113" インダストリー名="製造"/><row チャネルID="CC3" チャネル名="卸売" プロダクトID="PP19" プロダクト名="ﾓﾆﾀｰ 15 Super VGA" 売上="17570" インダストリーID="GG114" インダストリー名="機械"/><row チャネルID="CC3" チャネル名="卸売" プロダクトID="PP19" プロダクト名="ﾓﾆﾀｰ 15 Super VGA" 売上="44595" インダストリーID="GG115" インダストリー名="防衛"/><row チャネルID="CC3" チャネル名="卸売" プロダクトID="PP19" プロダクト名="ﾓﾆﾀｰ 15 Super VGA" 売上="73657" インダストリーID="GG116" インダストリー名="コンサルティング"/><row チャネルID="CC3" チャネル名="卸売" プロダクトID="PP19" プロダクト名="ﾓﾆﾀｰ 15 Super VGA" 売上="66431" インダストリーID="GG117" インダストリー名="ＳＩ"/><row チャネルID="CC3" チャネル名="卸売" プロダクトID="PP19" プロダクト名="ﾓﾆﾀｰ 15 Super VGA" 売上="22952" インダストリーID="GG118" インダストリー名="航空宇宙"/><row チャネルID="CC3" チャネル名="卸売" プロダクトID="PP19" プロダクト名="ﾓﾆﾀｰ 15 Super VGA" 売上="52965" インダストリーID="GG119" インダストリー名="転売"/><row チャネルID="CC3" チャネル名="卸売" プロダクトID="PP19" プロダクト名="ﾓﾆﾀｰ 15 Super VGA" 売上="12583" インダストリーID="GG120" インダストリー名="政府"/><row チャネルID="CC3" チャネル名="卸売" プロダクトID="PP19" プロダクト名="ﾓﾆﾀｰ 15 Super VGA" 売上="482" インダストリーID="GG121" インダストリー名="教育"/><row チャネルID="CC3" チャネル名="卸売" プロダクトID="PP20" プロダクト名="ﾓﾆﾀｰ 19 Super VGA" 売上="31124" インダストリーID="GG113" インダストリー名="製造"/><row チャネルID="CC3" チャネル名="卸売" プロダクトID="PP20" プロダクト名="ﾓﾆﾀｰ 19 Super VGA" 売上="12290" インダストリーID="GG114" インダストリー名="機械"/><row チャネルID="CC3" チャネル名="卸売" プロダクトID="PP20" プロダクト名="ﾓﾆﾀｰ 19 Super VGA" 売上="33074" インダストリーID="GG115" インダストリー名="防衛"/><row チャネルID="CC3" チャネル名="卸売" プロダクトID="PP20" プロダクト名="ﾓﾆﾀｰ 19 Super VGA" 売上="50293" インダストリーID="GG116" インダストリー名="コンサルティング"/><row チャネルID="CC3" チャネル名="卸売" プロダクトID="PP20" プロダクト名="ﾓﾆﾀｰ 19 Super VGA" 売上="49866" インダストリーID="GG117" インダストリー名="ＳＩ"/><row チャネルID="CC3" チャネル名="卸売" プロダクトID="PP20" プロダクト名="ﾓﾆﾀｰ 19 Super VGA" 売上="16580" インダストリーID="GG118" インダストリー名="航空宇宙"/><row チャネルID="CC3" チャネル名="卸売" プロダクトID="PP20" プロダクト名="ﾓﾆﾀｰ 19 Super VGA" 売上="42537" インダストリーID="GG119" インダストリー名="転売"/><row チャネルID="CC3" チャネル名="卸売" プロダクトID="PP20" プロダクト名="ﾓﾆﾀｰ 19 Super VGA" 売上="8356" インダストリーID="GG120" インダストリー名="政府"/><row チャネルID="CC3" チャネル名="卸売" プロダクトID="PP20" プロダクト名="ﾓﾆﾀｰ 19 Super VGA" 売上="545" インダストリーID="GG121" インダストリー名="教育"/><row チャネルID="CC3" チャネル名="卸売" プロダクトID="PP21" プロダクト名="Envoy 内蔵キーボード" 売上="20061" インダストリーID="GG113" インダストリー名="製造"/><row チャネルID="CC3" チャネル名="卸売" プロダクトID="PP21" プロダクト名="Envoy 内蔵キーボード" 売上="8174" インダストリーID="GG114" インダストリー名="機械"/><row チャネルID="CC3" チャネル名="卸売" プロダクトID="PP21" プロダクト名="Envoy 内蔵キーボード" 売上="21997" インダストリーID="GG115" インダストリー名="防衛"/><row チャネルID="CC3" チャネル名="卸売" プロダクトID="PP21" プロダクト名="Envoy 内蔵キーボード" 売上="34351" インダストリーID="GG116" インダストリー名="コンサルティング"/><row チャネルID="CC3" チャネル名="卸売" プロダクトID="PP21" プロダクト名="Envoy 内蔵キーボード" 売上="34752" インダストリーID="GG117" インダストリー名="ＳＩ"/><row チャネルID="CC3" チャネル名="卸売" プロダクトID="PP21" プロダクト名="Envoy 内蔵キーボード" 売上="9669" インダストリーID="GG118" インダストリー名="航空宇宙"/><row チャネルID="CC3" チャネル名="卸売" プロダクトID="PP21" プロダクト名="Envoy 内蔵キーボード" 売上="27513" インダストリーID="GG119" インダストリー名="転売"/><row チャネルID="CC3" チャネル名="卸売" プロダクトID="PP21" プロダクト名="Envoy 内蔵キーボード" 売上="5935" インダストリーID="GG120" インダストリー名="政府"/><row チャネルID="CC3" チャネル名="卸売" プロダクトID="PP21" プロダクト名="Envoy 内蔵キーボード" 売上="351" インダストリーID="GG121" インダストリー名="教育"/><row チャネルID="CC3" チャネル名="卸売" プロダクトID="PP22" プロダクト名="外付け 101キーボード" 売上="16546" インダストリーID="GG113" インダストリー名="製造"/><row チャネルID="CC3" チャネル名="卸売" プロダクトID="PP22" プロダクト名="外付け 101キーボード" 売上="5819" インダストリーID="GG114" インダストリー名="機械"/><row チャネルID="CC3" チャネル名="卸売" プロダクトID="PP22" プロダクト名="外付け 101キーボード" 売上="15816" インダストリーID="GG115" インダストリー名="防衛"/><row チャネルID="CC3" チャネル名="卸売" プロダクトID="PP22" プロダクト名="外付け 101キーボード" 売上="25016" インダストリーID="GG116" インダストリー名="コンサルティング"/><row チャネルID="CC3" チャネル名="卸売" プロダクトID="PP22" プロダクト名="外付け 101キーボード" 売上="29142" インダストリーID="GG117" インダストリー名="ＳＩ"/><row チャネルID="CC3" チャネル名="卸売" プロダクトID="PP22" プロダクト名="外付け 101キーボード" 売上="9054" インダストリーID="GG118" インダストリー名="航空宇宙"/><row チャネルID="CC3" チャネル名="卸売" プロダクトID="PP22" プロダクト名="外付け 101キーボード" 売上="20730" インダストリーID="GG119" インダストリー名="転売"/><row チャネルID="CC3" チャネル名="卸売" プロダクトID="PP22" プロダクト名="外付け 101キーボード" 売上="4501" インダストリーID="GG120" インダストリー名="政府"/><row チャネルID="CC3" チャネル名="卸売" プロダクトID="PP22" プロダクト名="外付け 101キーボード" 売上="249" インダストリーID="GG121" インダストリー名="教育"/><row チャネルID="CC3" チャネル名="卸売" プロダクトID="PP23" プロダクト名="PCMCIA ﾓﾃﾞﾑ/FAX 28800bps" 売上="68726" インダストリーID="GG113" インダストリー名="製造"/><row チャネルID="CC3" チャネル名="卸売" プロダクトID="PP23" プロダクト名="PCMCIA ﾓﾃﾞﾑ/FAX 28800bps" 売上="29435" インダストリーID="GG114" インダストリー名="機械"/><row チャネルID="CC3" チャネル名="卸売" プロダクトID="PP23" プロダクト名="PCMCIA ﾓﾃﾞﾑ/FAX 28800bps" 売上="71271" インダストリーID="GG115" インダストリー名="防衛"/><row チャネルID="CC3" チャネル名="卸売" プロダクトID="PP23" プロダクト名="PCMCIA ﾓﾃﾞﾑ/FAX 28800bps" 売上="116030" インダストリーID="GG116" インダストリー名="コンサルティング"/><row チャネルID="CC3" チャネル名="卸売" プロダクトID="PP23" プロダクト名="PCMCIA ﾓﾃﾞﾑ/FAX 28800bps" 売上="133618" インダストリーID="GG117" インダストリー名="ＳＩ"/><row チャネルID="CC3" チャネル名="卸売" プロダクトID="PP23" プロダクト名="PCMCIA ﾓﾃﾞﾑ/FAX 28800bps" 売上="38389" インダストリーID="GG118" インダストリー名="航空宇宙"/><row チャネルID="CC3" チャネル名="卸売" プロダクトID="PP23" プロダクト名="PCMCIA ﾓﾃﾞﾑ/FAX 28800bps" 売上="91941" インダストリーID="GG119" インダストリー名="転売"/><row チャネルID="CC3" チャネル名="卸売" プロダクトID="PP23" プロダクト名="PCMCIA ﾓﾃﾞﾑ/FAX 28800bps" 売上="18966" インダストリーID="GG120" インダストリー名="政府"/><row チャネルID="CC3" チャネル名="卸売" プロダクトID="PP23" プロダクト名="PCMCIA ﾓﾃﾞﾑ/FAX 28800bps" 売上="1178" インダストリーID="GG121" インダストリー名="教育"/><row チャネルID="CC3" チャネル名="卸売" プロダクトID="PP24" プロダクト名="SIMM- 8MB PCMCIAIIｶｰﾄﾞ" 売上="50673" インダストリーID="GG113" インダストリー名="製造"/><row チャネルID="CC3" チャネル名="卸売" プロダクトID="PP24" プロダクト名="SIMM- 8MB PCMCIAIIｶｰﾄﾞ" 売上="18134" インダストリーID="GG114" インダストリー名="機械"/><row チャネルID="CC3" チャネル名="卸売" プロダクトID="PP24" プロダクト名="SIMM- 8MB PCMCIAIIｶｰﾄﾞ" 売上="51636" インダストリーID="GG115" インダストリー名="防衛"/><row チャネルID="CC3" チャネル名="卸売" プロダクトID="PP24" プロダクト名="SIMM- 8MB PCMCIAIIｶｰﾄﾞ" 売上="85723" インダストリーID="GG116" インダストリー名="コンサルティング"/><row チャネルID="CC3" チャネル名="卸売" プロダクトID="PP24" プロダクト名="SIMM- 8MB PCMCIAIIｶｰﾄﾞ" 売上="88422" インダストリーID="GG117" インダストリー名="ＳＩ"/><row チャネルID="CC3" チャネル名="卸売" プロダクトID="PP24" プロダクト名="SIMM- 8MB PCMCIAIIｶｰﾄﾞ" 売上="24763" インダストリーID="GG118" インダストリー名="航空宇宙"/><row チャネルID="CC3" チャネル名="卸売" プロダクトID="PP24" プロダクト名="SIMM- 8MB PCMCIAIIｶｰﾄﾞ" 売上="66038" インダストリーID="GG119" インダストリー名="転売"/><row チャネルID="CC3" チャネル名="卸売" プロダクトID="PP24" プロダクト名="SIMM- 8MB PCMCIAIIｶｰﾄﾞ" 売上="14486" インダストリーID="GG120" インダストリー名="政府"/><row チャネルID="CC3" チャネル名="卸売" プロダクトID="PP24" プロダクト名="SIMM- 8MB PCMCIAIIｶｰﾄﾞ" 売上="697" インダストリーID="GG121" インダストリー名="教育"/><row チャネルID="CC3" チャネル名="卸売" プロダクトID="PP25" プロダクト名="SIMM- 16MB PCMCIAIIｶｰﾄﾞ" 売上="26846" インダストリーID="GG113" インダストリー名="製造"/><row チャネルID="CC3" チャネル名="卸売" プロダクトID="PP25" プロダクト名="SIMM- 16MB PCMCIAIIｶｰﾄﾞ" 売上="11842" インダストリーID="GG114" インダストリー名="機械"/><row チャネルID="CC3" チャネル名="卸売" プロダクトID="PP25" プロダクト名="SIMM- 16MB PCMCIAIIｶｰﾄﾞ" 売上="29476" インダストリーID="GG115" インダストリー名="防衛"/><row チャネルID="CC3" チャネル名="卸売" プロダクトID="PP25" プロダクト名="SIMM- 16MB PCMCIAIIｶｰﾄﾞ" 売上="47093" インダストリーID="GG116" インダストリー名="コンサルティング"/><row チャネルID="CC3" チャネル名="卸売" プロダクトID="PP25" プロダクト名="SIMM- 16MB PCMCIAIIｶｰﾄﾞ" 売上="53330" インダストリーID="GG117" インダストリー名="ＳＩ"/><row チャネルID="CC3" チャネル名="卸売" プロダクトID="PP25" プロダクト名="SIMM- 16MB PCMCIAIIｶｰﾄﾞ" 売上="12068" インダストリーID="GG118" インダストリー名="航空宇宙"/><row チャネルID="CC3" チャネル名="卸売" プロダクトID="PP25" プロダクト名="SIMM- 16MB PCMCIAIIｶｰﾄﾞ" 売上="40552" インダストリーID="GG119" インダストリー名="転売"/><row チャネルID="CC3" チャネル名="卸売" プロダクトID="PP25" プロダクト名="SIMM- 16MB PCMCIAIIｶｰﾄﾞ" 売上="7672" インダストリーID="GG120" インダストリー名="政府"/><row チャネルID="CC3" チャネル名="卸売" プロダクトID="PP25" プロダクト名="SIMM- 16MB PCMCIAIIｶｰﾄﾞ" 売上="414" インダストリーID="GG121" インダストリー名="教育"/><row チャネルID="CC3" チャネル名="卸売" プロダクトID="PP26" プロダクト名="ﾏﾙﾁﾒﾃﾞｨｱ･ｽﾋﾟｰｶ" 売上="8927" インダストリーID="GG113" インダストリー名="製造"/><row チャネルID="CC3" チャネル名="卸売" プロダクトID="PP26" プロダクト名="ﾏﾙﾁﾒﾃﾞｨｱ･ｽﾋﾟｰｶ" 売上="3531" インダストリーID="GG114" インダストリー名="機械"/><row チャネルID="CC3" チャネル名="卸売" プロダクトID="PP26" プロダクト名="ﾏﾙﾁﾒﾃﾞｨｱ･ｽﾋﾟｰｶ" 売上="9433" インダストリーID="GG115" インダストリー名="防衛"/><row チャネルID="CC3" チャネル名="卸売" プロダクトID="PP26" プロダクト名="ﾏﾙﾁﾒﾃﾞｨｱ･ｽﾋﾟｰｶ" 売上="13345" インダストリーID="GG116" インダストリー名="コンサルティング"/><row チャネルID="CC3" チャネル名="卸売" プロダクトID="PP26" プロダクト名="ﾏﾙﾁﾒﾃﾞｨｱ･ｽﾋﾟｰｶ" 売上="14395" インダストリーID="GG117" インダストリー名="ＳＩ"/><row チャネルID="CC3" チャネル名="卸売" プロダクトID="PP26" プロダクト名="ﾏﾙﾁﾒﾃﾞｨｱ･ｽﾋﾟｰｶ" 売上="3951" インダストリーID="GG118" インダストリー名="航空宇宙"/><row チャネルID="CC3" チャネル名="卸売" プロダクトID="PP26" プロダクト名="ﾏﾙﾁﾒﾃﾞｨｱ･ｽﾋﾟｰｶ" 売上="11329" インダストリーID="GG119" インダストリー名="転売"/><row チャネルID="CC3" チャネル名="卸売" プロダクトID="PP26" プロダクト名="ﾏﾙﾁﾒﾃﾞｨｱ･ｽﾋﾟｰｶ" 売上="2514" インダストリーID="GG120" インダストリー名="政府"/><row チャネルID="CC3" チャネル名="卸売" プロダクトID="PP26" プロダクト名="ﾏﾙﾁﾒﾃﾞｨｱ･ｽﾋﾟｰｶ" 売上="124" インダストリーID="GG121" インダストリー名="教育"/><row チャネルID="CC3" チャネル名="卸売" プロダクトID="PP27" プロダクト名="Unix/Windows 1ﾕｰｻﾞ･ﾊﾟｯｸ" 売上="42955" インダストリーID="GG113" インダストリー名="製造"/><row チャネルID="CC3" チャネル名="卸売" プロダクトID="PP27" プロダクト名="Unix/Windows 1ﾕｰｻﾞ･ﾊﾟｯｸ" 売上="15471" インダストリーID="GG114" インダストリー名="機械"/><row チャネルID="CC3" チャネル名="卸売" プロダクトID="PP27" プロダクト名="Unix/Windows 1ﾕｰｻﾞ･ﾊﾟｯｸ" 売上="49512" インダストリーID="GG115" インダストリー名="防衛"/><row チャネルID="CC3" チャネル名="卸売" プロダクトID="PP27" プロダクト名="Unix/Windows 1ﾕｰｻﾞ･ﾊﾟｯｸ" 売上="76832" インダストリーID="GG116" インダストリー名="コンサルティング"/><row チャネルID="CC3" チャネル名="卸売" プロダクトID="PP27" プロダクト名="Unix/Windows 1ﾕｰｻﾞ･ﾊﾟｯｸ" 売上="84689" インダストリーID="GG117" インダストリー名="ＳＩ"/><row チャネルID="CC3" チャネル名="卸売" プロダクトID="PP27" プロダクト名="Unix/Windows 1ﾕｰｻﾞ･ﾊﾟｯｸ" 売上="20364" インダストリーID="GG118" インダストリー名="航空宇宙"/><row チャネルID="CC3" チャネル名="卸売" プロダクトID="PP27" プロダクト名="Unix/Windows 1ﾕｰｻﾞ･ﾊﾟｯｸ" 売上="59193" インダストリーID="GG119" インダストリー名="転売"/><row チャネルID="CC3" チャネル名="卸売" プロダクトID="PP27" プロダクト名="Unix/Windows 1ﾕｰｻﾞ･ﾊﾟｯｸ" 売上="13782" インダストリーID="GG120" インダストリー名="政府"/><row チャネルID="CC3" チャネル名="卸売" プロダクトID="PP27" プロダクト名="Unix/Windows 1ﾕｰｻﾞ･ﾊﾟｯｸ" 売上="767" インダストリーID="GG121" インダストリー名="教育"/><row チャネルID="CC3" チャネル名="卸売" プロダクトID="PP28" プロダクト名="Unix/Windows 5ﾕｰｻﾞ･ﾊﾟｯｸ" 売上="3409" インダストリーID="GG113" インダストリー名="製造"/><row チャネルID="CC3" チャネル名="卸売" プロダクトID="PP28" プロダクト名="Unix/Windows 5ﾕｰｻﾞ･ﾊﾟｯｸ" 売上="1242" インダストリーID="GG114" インダストリー名="機械"/><row チャネルID="CC3" チャネル名="卸売" プロダクトID="PP28" プロダクト名="Unix/Windows 5ﾕｰｻﾞ･ﾊﾟｯｸ" 売上="3493" インダストリーID="GG115" インダストリー名="防衛"/><row チャネルID="CC3" チャネル名="卸売" プロダクトID="PP28" プロダクト名="Unix/Windows 5ﾕｰｻﾞ･ﾊﾟｯｸ" 売上="5226" インダストリーID="GG116" インダストリー名="コンサルティング"/><row チャネルID="CC3" チャネル名="卸売" プロダクトID="PP28" プロダクト名="Unix/Windows 5ﾕｰｻﾞ･ﾊﾟｯｸ" 売上="5820" インダストリーID="GG117" インダストリー名="ＳＩ"/><row チャネルID="CC3" チャネル名="卸売" プロダクトID="PP28" プロダクト名="Unix/Windows 5ﾕｰｻﾞ･ﾊﾟｯｸ" 売上="1384" インダストリーID="GG118" インダストリー名="航空宇宙"/><row チャネルID="CC3" チャネル名="卸売" プロダクトID="PP28" プロダクト名="Unix/Windows 5ﾕｰｻﾞ･ﾊﾟｯｸ" 売上="4594" インダストリーID="GG119" インダストリー名="転売"/><row チャネルID="CC3" チャネル名="卸売" プロダクトID="PP28" プロダクト名="Unix/Windows 5ﾕｰｻﾞ･ﾊﾟｯｸ" 売上="911" インダストリーID="GG120" インダストリー名="政府"/><row チャネルID="CC3" チャネル名="卸売" プロダクトID="PP28" プロダクト名="Unix/Windows 5ﾕｰｻﾞ･ﾊﾟｯｸ" 売上="0" インダストリーID="GG121" インダストリー名="教育"/><row チャネルID="CC3" チャネル名="卸売" プロダクトID="PP29" プロダクト名="マウス・パッド" 売上="457" インダストリーID="GG113" インダストリー名="製造"/><row チャネルID="CC3" チャネル名="卸売" プロダクトID="PP29" プロダクト名="マウス・パッド" 売上="196" インダストリーID="GG114" インダストリー名="機械"/><row チャネルID="CC3" チャネル名="卸売" プロダクトID="PP29" プロダクト名="マウス・パッド" 売上="532" インダストリーID="GG115" インダストリー名="防衛"/><row チャネルID="CC3" チャネル名="卸売" プロダクトID="PP29" プロダクト名="マウス・パッド" 売上="866" インダストリーID="GG116" インダストリー名="コンサルティング"/><row チャネルID="CC3" チャネル名="卸売" プロダクトID="PP29" プロダクト名="マウス・パッド" 売上="852" インダストリーID="GG117" インダストリー名="ＳＩ"/><row チャネルID="CC3" チャネル名="卸売" プロダクトID="PP29" プロダクト名="マウス・パッド" 売上="291" インダストリーID="GG118" インダストリー名="航空宇宙"/><row チャネルID="CC3" チャネル名="卸売" プロダクトID="PP29" プロダクト名="マウス・パッド" 売上="715" インダストリーID="GG119" インダストリー名="転売"/><row チャネルID="CC3" チャネル名="卸売" プロダクトID="PP29" プロダクト名="マウス・パッド" 売上="153" インダストリーID="GG120" インダストリー名="政府"/><row チャネルID="CC3" チャネル名="卸売" プロダクトID="PP29" プロダクト名="マウス・パッド" 売上="8" インダストリーID="GG121" インダストリー名="教育"/><row チャネルID="CC3" チャネル名="卸売" プロダクトID="PP30" プロダクト名="2.88MB  3.5 FD" 売上="32615" インダストリーID="GG113" インダストリー名="製造"/><row チャネルID="CC3" チャネル名="卸売" プロダクトID="PP30" プロダクト名="2.88MB  3.5 FD" 売上="14201" インダストリーID="GG114" インダストリー名="機械"/><row チャネルID="CC3" チャネル名="卸売" プロダクトID="PP30" プロダクト名="2.88MB  3.5 FD" 売上="34510" インダストリーID="GG115" インダストリー名="防衛"/><row チャネルID="CC3" チャネル名="卸売" プロダクトID="PP30" プロダクト名="2.88MB  3.5 FD" 売上="70624" インダストリーID="GG116" インダストリー名="コンサルティング"/><row チャネルID="CC3" チャネル名="卸売" プロダクトID="PP30" プロダクト名="2.88MB  3.5 FD" 売上="70797" インダストリーID="GG117" インダストリー名="ＳＩ"/><row チャネルID="CC3" チャネル名="卸売" プロダクトID="PP30" プロダクト名="2.88MB  3.5 FD" 売上="15876" インダストリーID="GG118" インダストリー名="航空宇宙"/><row チャネルID="CC3" チャネル名="卸売" プロダクトID="PP30" プロダクト名="2.88MB  3.5 FD" 売上="52960" インダストリーID="GG119" インダストリー名="転売"/><row チャネルID="CC3" チャネル名="卸売" プロダクトID="PP30" プロダクト名="2.88MB  3.5 FD" 売上="10859" インダストリーID="GG120" インダストリー名="政府"/><row チャネルID="CC3" チャネル名="卸売" プロダクトID="PP30" プロダクト名="2.88MB  3.5 FD" 売上="569" インダストリーID="GG121" インダストリー名="教育"/><row チャネルID="CC3" チャネル名="卸売" プロダクトID="PP31" プロダクト名="ﾏﾙﾁﾒﾃﾞｨｱ･ｽﾋﾟｰｶ" 売上="8364" インダストリーID="GG113" インダストリー名="製造"/><row チャネルID="CC3" チャネル名="卸売" プロダクトID="PP31" プロダクト名="ﾏﾙﾁﾒﾃﾞｨｱ･ｽﾋﾟｰｶ" 売上="2987" インダストリーID="GG114" インダストリー名="機械"/><row チャネルID="CC3" チャネル名="卸売" プロダクトID="PP31" プロダクト名="ﾏﾙﾁﾒﾃﾞｨｱ･ｽﾋﾟｰｶ" 売上="8739" インダストリーID="GG115" インダストリー名="防衛"/><row チャネルID="CC3" チャネル名="卸売" プロダクトID="PP31" プロダクト名="ﾏﾙﾁﾒﾃﾞｨｱ･ｽﾋﾟｰｶ" 売上="14268" インダストリーID="GG116" インダストリー名="コンサルティング"/><row チャネルID="CC3" チャネル名="卸売" プロダクトID="PP31" プロダクト名="ﾏﾙﾁﾒﾃﾞｨｱ･ｽﾋﾟｰｶ" 売上="14812" インダストリーID="GG117" インダストリー名="ＳＩ"/><row チャネルID="CC3" チャネル名="卸売" プロダクトID="PP31" プロダクト名="ﾏﾙﾁﾒﾃﾞｨｱ･ｽﾋﾟｰｶ" 売上="4772" インダストリーID="GG118" インダストリー名="航空宇宙"/><row チャネルID="CC3" チャネル名="卸売" プロダクトID="PP31" プロダクト名="ﾏﾙﾁﾒﾃﾞｨｱ･ｽﾋﾟｰｶ" 売上="11705" インダストリーID="GG119" インダストリー名="転売"/><row チャネルID="CC3" チャネル名="卸売" プロダクトID="PP31" プロダクト名="ﾏﾙﾁﾒﾃﾞｨｱ･ｽﾋﾟｰｶ" 売上="2241" インダストリーID="GG120" インダストリー名="政府"/><row チャネルID="CC3" チャネル名="卸売" プロダクトID="PP31" プロダクト名="ﾏﾙﾁﾒﾃﾞｨｱ･ｽﾋﾟｰｶ" 売上="157" インダストリーID="GG121" インダストリー名="教育"/><row チャネルID="CC3" チャネル名="卸売" プロダクトID="PP32" プロダクト名="PCMCIA ﾓﾃﾞﾑ/FAX 19200bps" 売上="6354" インダストリーID="GG113" インダストリー名="製造"/><row チャネルID="CC3" チャネル名="卸売" プロダクトID="PP32" プロダクト名="PCMCIA ﾓﾃﾞﾑ/FAX 19200bps" 売上="2323" インダストリーID="GG114" インダストリー名="機械"/><row チャネルID="CC3" チャネル名="卸売" プロダクトID="PP32" プロダクト名="PCMCIA ﾓﾃﾞﾑ/FAX 19200bps" 売上="7157" インダストリーID="GG115" インダストリー名="防衛"/><row チャネルID="CC3" チャネル名="卸売" プロダクトID="PP32" プロダクト名="PCMCIA ﾓﾃﾞﾑ/FAX 19200bps" 売上="11196" インダストリーID="GG116" インダストリー名="コンサルティング"/><row チャネルID="CC3" チャネル名="卸売" プロダクトID="PP32" プロダクト名="PCMCIA ﾓﾃﾞﾑ/FAX 19200bps" 売上="11869" インダストリーID="GG117" インダストリー名="ＳＩ"/><row チャネルID="CC3" チャネル名="卸売" プロダクトID="PP32" プロダクト名="PCMCIA ﾓﾃﾞﾑ/FAX 19200bps" 売上="3117" インダストリーID="GG118" インダストリー名="航空宇宙"/><row チャネルID="CC3" チャネル名="卸売" プロダクトID="PP32" プロダクト名="PCMCIA ﾓﾃﾞﾑ/FAX 19200bps" 売上="8442" インダストリーID="GG119" インダストリー名="転売"/><row チャネルID="CC3" チャネル名="卸売" プロダクトID="PP32" プロダクト名="PCMCIA ﾓﾃﾞﾑ/FAX 19200bps" 売上="1880" インダストリーID="GG120" インダストリー名="政府"/><row チャネルID="CC3" チャネル名="卸売" プロダクトID="PP32" プロダクト名="PCMCIA ﾓﾃﾞﾑ/FAX 19200bps" 売上="99" インダストリーID="GG121" インダストリー名="教育"/><row チャネルID="CC4" チャネル名="カタログ" プロダクトID="PP11" プロダクト名="Envoy ｽﾀﾝﾀﾞｰﾄﾞ" 売上="772823" インダストリーID="GG113" インダストリー名="製造"/><row チャネルID="CC4" チャネル名="カタログ" プロダクトID="PP11" プロダクト名="Envoy ｽﾀﾝﾀﾞｰﾄﾞ" 売上="291192" インダストリーID="GG114" インダストリー名="機械"/><row チャネルID="CC4" チャネル名="カタログ" プロダクトID="PP11" プロダクト名="Envoy ｽﾀﾝﾀﾞｰﾄﾞ" 売上="960512" インダストリーID="GG115" インダストリー名="防衛"/><row チャネルID="CC4" チャネル名="カタログ" プロダクトID="PP11" プロダクト名="Envoy ｽﾀﾝﾀﾞｰﾄﾞ" 売上="1450607" インダストリーID="GG116" インダストリー名="コンサルティング"/><row チャネルID="CC4" チャネル名="カタログ" プロダクトID="PP11" プロダクト名="Envoy ｽﾀﾝﾀﾞｰﾄﾞ" 売上="1384647" インダストリーID="GG117" インダストリー名="ＳＩ"/><row チャネルID="CC4" チャネル名="カタログ" プロダクトID="PP11" プロダクト名="Envoy ｽﾀﾝﾀﾞｰﾄﾞ" 売上="326188" インダストリーID="GG118" インダストリー名="航空宇宙"/><row チャネルID="CC4" チャネル名="カタログ" プロダクトID="PP11" プロダクト名="Envoy ｽﾀﾝﾀﾞｰﾄﾞ" 売上="1141949" インダストリーID="GG119" インダストリー名="転売"/><row チャネルID="CC4" チャネル名="カタログ" プロダクトID="PP11" プロダクト名="Envoy ｽﾀﾝﾀﾞｰﾄﾞ" 売上="275779" インダストリーID="GG120" インダストリー名="政府"/><row チャネルID="CC4" チャネル名="カタログ" プロダクトID="PP11" プロダクト名="Envoy ｽﾀﾝﾀﾞｰﾄﾞ" 売上="10329" インダストリーID="GG121" インダストリー名="教育"/><row チャネルID="CC4" チャネル名="カタログ" プロダクトID="PP12" プロダクト名="Envoy ｴｸﾞｾﾞｸﾃｨﾌﾞ" 売上="144419" インダストリーID="GG113" インダストリー名="製造"/><row チャネルID="CC4" チャネル名="カタログ" プロダクトID="PP12" プロダクト名="Envoy ｴｸﾞｾﾞｸﾃｨﾌﾞ" 売上="62490" インダストリーID="GG114" インダストリー名="機械"/><row チャネルID="CC4" チャネル名="カタログ" プロダクトID="PP12" プロダクト名="Envoy ｴｸﾞｾﾞｸﾃｨﾌﾞ" 売上="139816" インダストリーID="GG115" インダストリー名="防衛"/><row チャネルID="CC4" チャネル名="カタログ" プロダクトID="PP12" プロダクト名="Envoy ｴｸﾞｾﾞｸﾃｨﾌﾞ" 売上="241457" インダストリーID="GG116" インダストリー名="コンサルティング"/><row チャネルID="CC4" チャネル名="カタログ" プロダクトID="PP12" プロダクト名="Envoy ｴｸﾞｾﾞｸﾃｨﾌﾞ" 売上="249103" インダストリーID="GG117" インダストリー名="ＳＩ"/><row チャネルID="CC4" チャネル名="カタログ" プロダクトID="PP12" プロダクト名="Envoy ｴｸﾞｾﾞｸﾃｨﾌﾞ" 売上="52682" インダストリーID="GG118" インダストリー名="航空宇宙"/><row チャネルID="CC4" チャネル名="カタログ" プロダクトID="PP12" プロダクト名="Envoy ｴｸﾞｾﾞｸﾃｨﾌﾞ" 売上="202562" インダストリーID="GG119" インダストリー名="転売"/><row チャネルID="CC4" チャネル名="カタログ" プロダクトID="PP12" プロダクト名="Envoy ｴｸﾞｾﾞｸﾃｨﾌﾞ" 売上="40964" インダストリーID="GG120" インダストリー名="政府"/><row チャネルID="CC4" チャネル名="カタログ" プロダクトID="PP12" プロダクト名="Envoy ｴｸﾞｾﾞｸﾃｨﾌﾞ" 売上="1009" インダストリーID="GG121" インダストリー名="教育"/><row チャネルID="CC4" チャネル名="カタログ" プロダクトID="PP13" プロダクト名="Envoy ｱﾝﾊﾞｻﾀﾞｰ" 売上="167041" インダストリーID="GG113" インダストリー名="製造"/><row チャネルID="CC4" チャネル名="カタログ" プロダクトID="PP13" プロダクト名="Envoy ｱﾝﾊﾞｻﾀﾞｰ" 売上="56932" インダストリーID="GG114" インダストリー名="機械"/><row チャネルID="CC4" チャネル名="カタログ" プロダクトID="PP13" プロダクト名="Envoy ｱﾝﾊﾞｻﾀﾞｰ" 売上="139578" インダストリーID="GG115" インダストリー名="防衛"/><row チャネルID="CC4" チャネル名="カタログ" プロダクトID="PP13" プロダクト名="Envoy ｱﾝﾊﾞｻﾀﾞｰ" 売上="270855" インダストリーID="GG116" インダストリー名="コンサルティング"/><row チャネルID="CC4" チャネル名="カタログ" プロダクトID="PP13" プロダクト名="Envoy ｱﾝﾊﾞｻﾀﾞｰ" 売上="264848" インダストリーID="GG117" インダストリー名="ＳＩ"/><row チャネルID="CC4" チャネル名="カタログ" プロダクトID="PP13" プロダクト名="Envoy ｱﾝﾊﾞｻﾀﾞｰ" 売上="57867" インダストリーID="GG118" インダストリー名="航空宇宙"/><row チャネルID="CC4" チャネル名="カタログ" プロダクトID="PP13" プロダクト名="Envoy ｱﾝﾊﾞｻﾀﾞｰ" 売上="197549" インダストリーID="GG119" インダストリー名="転売"/><row チャネルID="CC4" チャネル名="カタログ" プロダクトID="PP13" プロダクト名="Envoy ｱﾝﾊﾞｻﾀﾞｰ" 売上="45560" インダストリーID="GG120" インダストリー名="政府"/><row チャネルID="CC4" チャネル名="カタログ" プロダクトID="PP13" プロダクト名="Envoy ｱﾝﾊﾞｻﾀﾞｰ" 売上="1294" インダストリーID="GG121" インダストリー名="教育"/><row チャネルID="CC4" チャネル名="カタログ" プロダクトID="PP14" プロダクト名="Sentinel ｽﾀﾝﾀﾞｰﾄﾞ" 売上="505997" インダストリーID="GG113" インダストリー名="製造"/><row チャネルID="CC4" チャネル名="カタログ" プロダクトID="PP14" プロダクト名="Sentinel ｽﾀﾝﾀﾞｰﾄﾞ" 売上="204510" インダストリーID="GG114" インダストリー名="機械"/><row チャネルID="CC4" チャネル名="カタログ" プロダクトID="PP14" プロダクト名="Sentinel ｽﾀﾝﾀﾞｰﾄﾞ" 売上="524898" インダストリーID="GG115" インダストリー名="防衛"/><row チャネルID="CC4" チャネル名="カタログ" プロダクトID="PP14" プロダクト名="Sentinel ｽﾀﾝﾀﾞｰﾄﾞ" 売上="931702" インダストリーID="GG116" インダストリー名="コンサルティング"/><row チャネルID="CC4" チャネル名="カタログ" プロダクトID="PP14" プロダクト名="Sentinel ｽﾀﾝﾀﾞｰﾄﾞ" 売上="970383" インダストリーID="GG117" インダストリー名="ＳＩ"/><row チャネルID="CC4" チャネル名="カタログ" プロダクトID="PP14" プロダクト名="Sentinel ｽﾀﾝﾀﾞｰﾄﾞ" 売上="222051" インダストリーID="GG118" インダストリー名="航空宇宙"/><row チャネルID="CC4" チャネル名="カタログ" プロダクトID="PP14" プロダクト名="Sentinel ｽﾀﾝﾀﾞｰﾄﾞ" 売上="755371" インダストリーID="GG119" インダストリー名="転売"/><row チャネルID="CC4" チャネル名="カタログ" プロダクトID="PP14" プロダクト名="Sentinel ｽﾀﾝﾀﾞｰﾄﾞ" 売上="151760" インダストリーID="GG120" インダストリー名="政府"/><row チャネルID="CC4" チャネル名="カタログ" プロダクトID="PP14" プロダクト名="Sentinel ｽﾀﾝﾀﾞｰﾄﾞ" 売上="8196" インダストリーID="GG121" インダストリー名="教育"/><row チャネルID="CC4" チャネル名="カタログ" プロダクトID="PP15" プロダクト名="Sentinel ﾌｧｲﾅﾝｼｬﾙ" 売上="158438" インダストリーID="GG113" インダストリー名="製造"/><row チャネルID="CC4" チャネル名="カタログ" プロダクトID="PP15" プロダクト名="Sentinel ﾌｧｲﾅﾝｼｬﾙ" 売上="53232" インダストリーID="GG114" インダストリー名="機械"/><row チャネルID="CC4" チャネル名="カタログ" プロダクトID="PP15" プロダクト名="Sentinel ﾌｧｲﾅﾝｼｬﾙ" 売上="117116" インダストリーID="GG115" インダストリー名="防衛"/><row チャネルID="CC4" チャネル名="カタログ" プロダクトID="PP15" プロダクト名="Sentinel ﾌｧｲﾅﾝｼｬﾙ" 売上="244289" インダストリーID="GG116" インダストリー名="コンサルティング"/><row チャネルID="CC4" チャネル名="カタログ" プロダクトID="PP15" プロダクト名="Sentinel ﾌｧｲﾅﾝｼｬﾙ" 売上="272728" インダストリーID="GG117" インダストリー名="ＳＩ"/><row チャネルID="CC4" チャネル名="カタログ" プロダクトID="PP15" プロダクト名="Sentinel ﾌｧｲﾅﾝｼｬﾙ" 売上="58529" インダストリーID="GG118" インダストリー名="航空宇宙"/><row チャネルID="CC4" チャネル名="カタログ" プロダクトID="PP15" プロダクト名="Sentinel ﾌｧｲﾅﾝｼｬﾙ" 売上="213382" インダストリーID="GG119" インダストリー名="転売"/><row チャネルID="CC4" チャネル名="カタログ" プロダクトID="PP15" プロダクト名="Sentinel ﾌｧｲﾅﾝｼｬﾙ" 売上="51122" インダストリーID="GG120" インダストリー名="政府"/><row チャネルID="CC4" チャネル名="カタログ" プロダクトID="PP15" プロダクト名="Sentinel ﾌｧｲﾅﾝｼｬﾙ" 売上="1894" インダストリーID="GG121" インダストリー名="教育"/><row チャネルID="CC4" チャネル名="カタログ" プロダクトID="PP16" プロダクト名="Sentinel ﾏﾙﾁﾒﾃﾞｨｱ" 売上="447610" インダストリーID="GG113" インダストリー名="製造"/><row チャネルID="CC4" チャネル名="カタログ" プロダクトID="PP16" プロダクト名="Sentinel ﾏﾙﾁﾒﾃﾞｨｱ" 売上="167959" インダストリーID="GG114" インダストリー名="機械"/><row チャネルID="CC4" チャネル名="カタログ" プロダクトID="PP16" プロダクト名="Sentinel ﾏﾙﾁﾒﾃﾞｨｱ" 売上="551984" インダストリーID="GG115" インダストリー名="防衛"/><row チャネルID="CC4" チャネル名="カタログ" プロダクトID="PP16" プロダクト名="Sentinel ﾏﾙﾁﾒﾃﾞｨｱ" 売上="787771" インダストリーID="GG116" インダストリー名="コンサルティング"/><row チャネルID="CC4" チャネル名="カタログ" プロダクトID="PP16" プロダクト名="Sentinel ﾏﾙﾁﾒﾃﾞｨｱ" 売上="752752" インダストリーID="GG117" インダストリー名="ＳＩ"/><row チャネルID="CC4" チャネル名="カタログ" プロダクトID="PP16" プロダクト名="Sentinel ﾏﾙﾁﾒﾃﾞｨｱ" 売上="221464" インダストリーID="GG118" インダストリー名="航空宇宙"/><row チャネルID="CC4" チャネル名="カタログ" プロダクトID="PP16" プロダクト名="Sentinel ﾏﾙﾁﾒﾃﾞｨｱ" 売上="666589" インダストリーID="GG119" インダストリー名="転売"/><row チャネルID="CC4" チャネル名="カタログ" プロダクトID="PP16" プロダクト名="Sentinel ﾏﾙﾁﾒﾃﾞｨｱ" 売上="135765" インダストリーID="GG120" インダストリー名="政府"/><row チャネルID="CC4" チャネル名="カタログ" プロダクトID="PP16" プロダクト名="Sentinel ﾏﾙﾁﾒﾃﾞｨｱ" 売上="5865" インダストリーID="GG121" インダストリー名="教育"/><row チャネルID="CC4" チャネル名="カタログ" プロダクトID="PP17" プロダクト名="ＯＳﾄﾞｷｭﾒﾝﾄ一式" 売上="8630" インダストリーID="GG113" インダストリー名="製造"/><row チャネルID="CC4" チャネル名="カタログ" プロダクトID="PP17" プロダクト名="ＯＳﾄﾞｷｭﾒﾝﾄ一式" 売上="3518" インダストリーID="GG114" インダストリー名="機械"/><row チャネルID="CC4" チャネル名="カタログ" プロダクトID="PP17" プロダクト名="ＯＳﾄﾞｷｭﾒﾝﾄ一式" 売上="9889" インダストリーID="GG115" インダストリー名="防衛"/><row チャネルID="CC4" チャネル名="カタログ" プロダクトID="PP17" プロダクト名="ＯＳﾄﾞｷｭﾒﾝﾄ一式" 売上="13859" インダストリーID="GG116" インダストリー名="コンサルティング"/><row チャネルID="CC4" チャネル名="カタログ" プロダクトID="PP17" プロダクト名="ＯＳﾄﾞｷｭﾒﾝﾄ一式" 売上="15235" インダストリーID="GG117" インダストリー名="ＳＩ"/><row チャネルID="CC4" チャネル名="カタログ" プロダクトID="PP17" プロダクト名="ＯＳﾄﾞｷｭﾒﾝﾄ一式" 売上="4073" インダストリーID="GG118" インダストリー名="航空宇宙"/><row チャネルID="CC4" チャネル名="カタログ" プロダクトID="PP17" プロダクト名="ＯＳﾄﾞｷｭﾒﾝﾄ一式" 売上="10554" インダストリーID="GG119" インダストリー名="転売"/><row チャネルID="CC4" チャネル名="カタログ" プロダクトID="PP17" プロダクト名="ＯＳﾄﾞｷｭﾒﾝﾄ一式" 売上="2528" インダストリーID="GG120" インダストリー名="政府"/><row チャネルID="CC4" チャネル名="カタログ" プロダクトID="PP17" プロダクト名="ＯＳﾄﾞｷｭﾒﾝﾄ一式" 売上="133" インダストリーID="GG121" インダストリー名="教育"/><row チャネルID="CC4" チャネル名="カタログ" プロダクトID="PP18" プロダクト名="ﾉｰﾄPC ｷｬﾘﾝｸﾞ･ｹｰｽ" 売上="10454" インダストリーID="GG113" インダストリー名="製造"/><row チャネルID="CC4" チャネル名="カタログ" プロダクトID="PP18" プロダクト名="ﾉｰﾄPC ｷｬﾘﾝｸﾞ･ｹｰｽ" 売上="3661" インダストリーID="GG114" インダストリー名="機械"/><row チャネルID="CC4" チャネル名="カタログ" プロダクトID="PP18" プロダクト名="ﾉｰﾄPC ｷｬﾘﾝｸﾞ･ｹｰｽ" 売上="11239" インダストリーID="GG115" インダストリー名="防衛"/><row チャネルID="CC4" チャネル名="カタログ" プロダクトID="PP18" プロダクト名="ﾉｰﾄPC ｷｬﾘﾝｸﾞ･ｹｰｽ" 売上="16902" インダストリーID="GG116" インダストリー名="コンサルティング"/><row チャネルID="CC4" チャネル名="カタログ" プロダクトID="PP18" プロダクト名="ﾉｰﾄPC ｷｬﾘﾝｸﾞ･ｹｰｽ" 売上="21388" インダストリーID="GG117" インダストリー名="ＳＩ"/><row チャネルID="CC4" チャネル名="カタログ" プロダクトID="PP18" プロダクト名="ﾉｰﾄPC ｷｬﾘﾝｸﾞ･ｹｰｽ" 売上="5040" インダストリーID="GG118" インダストリー名="航空宇宙"/><row チャネルID="CC4" チャネル名="カタログ" プロダクトID="PP18" プロダクト名="ﾉｰﾄPC ｷｬﾘﾝｸﾞ･ｹｰｽ" 売上="13175" インダストリーID="GG119" インダストリー名="転売"/><row チャネルID="CC4" チャネル名="カタログ" プロダクトID="PP18" プロダクト名="ﾉｰﾄPC ｷｬﾘﾝｸﾞ･ｹｰｽ" 売上="3052" インダストリーID="GG120" インダストリー名="政府"/><row チャネルID="CC4" チャネル名="カタログ" プロダクトID="PP18" プロダクト名="ﾉｰﾄPC ｷｬﾘﾝｸﾞ･ｹｰｽ" 売上="165" インダストリーID="GG121" インダストリー名="教育"/><row チャネルID="CC4" チャネル名="カタログ" プロダクトID="PP19" プロダクト名="ﾓﾆﾀｰ 15 Super VGA" 売上="39959" インダストリーID="GG113" インダストリー名="製造"/><row チャネルID="CC4" チャネル名="カタログ" プロダクトID="PP19" プロダクト名="ﾓﾆﾀｰ 15 Super VGA" 売上="16651" インダストリーID="GG114" インダストリー名="機械"/><row チャネルID="CC4" チャネル名="カタログ" プロダクトID="PP19" プロダクト名="ﾓﾆﾀｰ 15 Super VGA" 売上="42554" インダストリーID="GG115" インダストリー名="防衛"/><row チャネルID="CC4" チャネル名="カタログ" プロダクトID="PP19" プロダクト名="ﾓﾆﾀｰ 15 Super VGA" 売上="81813" インダストリーID="GG116" インダストリー名="コンサルティング"/><row チャネルID="CC4" チャネル名="カタログ" プロダクトID="PP19" プロダクト名="ﾓﾆﾀｰ 15 Super VGA" 売上="74211" インダストリーID="GG117" インダストリー名="ＳＩ"/><row チャネルID="CC4" チャネル名="カタログ" プロダクトID="PP19" プロダクト名="ﾓﾆﾀｰ 15 Super VGA" 売上="17234" インダストリーID="GG118" インダストリー名="航空宇宙"/><row チャネルID="CC4" チャネル名="カタログ" プロダクトID="PP19" プロダクト名="ﾓﾆﾀｰ 15 Super VGA" 売上="59004" インダストリーID="GG119" インダストリー名="転売"/><row チャネルID="CC4" チャネル名="カタログ" プロダクトID="PP19" プロダクト名="ﾓﾆﾀｰ 15 Super VGA" 売上="14458" インダストリーID="GG120" インダストリー名="政府"/><row チャネルID="CC4" チャネル名="カタログ" プロダクトID="PP19" プロダクト名="ﾓﾆﾀｰ 15 Super VGA" 売上="488" インダストリーID="GG121" インダストリー名="教育"/><row チャネルID="CC4" チャネル名="カタログ" プロダクトID="PP20" プロダクト名="ﾓﾆﾀｰ 19 Super VGA" 売上="32125" インダストリーID="GG113" インダストリー名="製造"/><row チャネルID="CC4" チャネル名="カタログ" プロダクトID="PP20" プロダクト名="ﾓﾆﾀｰ 19 Super VGA" 売上="12034" インダストリーID="GG114" インダストリー名="機械"/><row チャネルID="CC4" チャネル名="カタログ" プロダクトID="PP20" プロダクト名="ﾓﾆﾀｰ 19 Super VGA" 売上="31838" インダストリーID="GG115" インダストリー名="防衛"/><row チャネルID="CC4" チャネル名="カタログ" プロダクトID="PP20" プロダクト名="ﾓﾆﾀｰ 19 Super VGA" 売上="50651" インダストリーID="GG116" インダストリー名="コンサルティング"/><row チャネルID="CC4" チャネル名="カタログ" プロダクトID="PP20" プロダクト名="ﾓﾆﾀｰ 19 Super VGA" 売上="60034" インダストリーID="GG117" インダストリー名="ＳＩ"/><row チャネルID="CC4" チャネル名="カタログ" プロダクトID="PP20" プロダクト名="ﾓﾆﾀｰ 19 Super VGA" 売上="18181" インダストリーID="GG118" インダストリー名="航空宇宙"/><row チャネルID="CC4" チャネル名="カタログ" プロダクトID="PP20" プロダクト名="ﾓﾆﾀｰ 19 Super VGA" 売上="45272" インダストリーID="GG119" インダストリー名="転売"/><row チャネルID="CC4" チャネル名="カタログ" プロダクトID="PP20" プロダクト名="ﾓﾆﾀｰ 19 Super VGA" 売上="8880" インダストリーID="GG120" インダストリー名="政府"/><row チャネルID="CC4" チャネル名="カタログ" プロダクトID="PP20" プロダクト名="ﾓﾆﾀｰ 19 Super VGA" 売上="457" インダストリーID="GG121" インダストリー名="教育"/><row チャネルID="CC4" チャネル名="カタログ" プロダクトID="PP21" プロダクト名="Envoy 内蔵キーボード" 売上="19977" インダストリーID="GG113" インダストリー名="製造"/><row チャネルID="CC4" チャネル名="カタログ" プロダクトID="PP21" プロダクト名="Envoy 内蔵キーボード" 売上="8895" インダストリーID="GG114" インダストリー名="機械"/><row チャネルID="CC4" チャネル名="カタログ" プロダクトID="PP21" プロダクト名="Envoy 内蔵キーボード" 売上="19905" インダストリーID="GG115" インダストリー名="防衛"/><row チャネルID="CC4" チャネル名="カタログ" プロダクトID="PP21" プロダクト名="Envoy 内蔵キーボード" 売上="38376" インダストリーID="GG116" インダストリー名="コンサルティング"/><row チャネルID="CC4" チャネル名="カタログ" プロダクトID="PP21" プロダクト名="Envoy 内蔵キーボード" 売上="39126" インダストリーID="GG117" インダストリー名="ＳＩ"/><row チャネルID="CC4" チャネル名="カタログ" プロダクトID="PP21" プロダクト名="Envoy 内蔵キーボード" 売上="8192" インダストリーID="GG118" インダストリー名="航空宇宙"/><row チャネルID="CC4" チャネル名="カタログ" プロダクトID="PP21" プロダクト名="Envoy 内蔵キーボード" 売上="29287" インダストリーID="GG119" インダストリー名="転売"/><row チャネルID="CC4" チャネル名="カタログ" プロダクトID="PP21" プロダクト名="Envoy 内蔵キーボード" 売上="6829" インダストリーID="GG120" インダストリー名="政府"/><row チャネルID="CC4" チャネル名="カタログ" プロダクトID="PP21" プロダクト名="Envoy 内蔵キーボード" 売上="362" インダストリーID="GG121" インダストリー名="教育"/><row チャネルID="CC4" チャネル名="カタログ" プロダクトID="PP22" プロダクト名="外付け 101キーボード" 売上="16379" インダストリーID="GG113" インダストリー名="製造"/><row チャネルID="CC4" チャネル名="カタログ" プロダクトID="PP22" プロダクト名="外付け 101キーボード" 売上="5919" インダストリーID="GG114" インダストリー名="機械"/><row チャネルID="CC4" チャネル名="カタログ" プロダクトID="PP22" プロダクト名="外付け 101キーボード" 売上="16637" インダストリーID="GG115" インダストリー名="防衛"/><row チャネルID="CC4" チャネル名="カタログ" プロダクトID="PP22" プロダクト名="外付け 101キーボード" 売上="27116" インダストリーID="GG116" インダストリー名="コンサルティング"/><row チャネルID="CC4" チャネル名="カタログ" プロダクトID="PP22" プロダクト名="外付け 101キーボード" 売上="33681" インダストリーID="GG117" インダストリー名="ＳＩ"/><row チャネルID="CC4" チャネル名="カタログ" プロダクトID="PP22" プロダクト名="外付け 101キーボード" 売上="9659" インダストリーID="GG118" インダストリー名="航空宇宙"/><row チャネルID="CC4" チャネル名="カタログ" プロダクトID="PP22" プロダクト名="外付け 101キーボード" 売上="23975" インダストリーID="GG119" インダストリー名="転売"/><row チャネルID="CC4" チャネル名="カタログ" プロダクトID="PP22" プロダクト名="外付け 101キーボード" 売上="5074" インダストリーID="GG120" インダストリー名="政府"/><row チャネルID="CC4" チャネル名="カタログ" プロダクトID="PP22" プロダクト名="外付け 101キーボード" 売上="219" インダストリーID="GG121" インダストリー名="教育"/><row チャネルID="CC4" チャネル名="カタログ" プロダクトID="PP23" プロダクト名="PCMCIA ﾓﾃﾞﾑ/FAX 28800bps" 売上="60704" インダストリーID="GG113" インダストリー名="製造"/><row チャネルID="CC4" チャネル名="カタログ" プロダクトID="PP23" プロダクト名="PCMCIA ﾓﾃﾞﾑ/FAX 28800bps" 売上="33301" インダストリーID="GG114" インダストリー名="機械"/><row チャネルID="CC4" チャネル名="カタログ" プロダクトID="PP23" プロダクト名="PCMCIA ﾓﾃﾞﾑ/FAX 28800bps" 売上="63519" インダストリーID="GG115" インダストリー名="防衛"/><row チャネルID="CC4" チャネル名="カタログ" プロダクトID="PP23" プロダクト名="PCMCIA ﾓﾃﾞﾑ/FAX 28800bps" 売上="130053" インダストリーID="GG116" インダストリー名="コンサルティング"/><row チャネルID="CC4" チャネル名="カタログ" プロダクトID="PP23" プロダクト名="PCMCIA ﾓﾃﾞﾑ/FAX 28800bps" 売上="136447" インダストリーID="GG117" インダストリー名="ＳＩ"/><row チャネルID="CC4" チャネル名="カタログ" プロダクトID="PP23" プロダクト名="PCMCIA ﾓﾃﾞﾑ/FAX 28800bps" 売上="39274" インダストリーID="GG118" インダストリー名="航空宇宙"/><row チャネルID="CC4" チャネル名="カタログ" プロダクトID="PP23" プロダクト名="PCMCIA ﾓﾃﾞﾑ/FAX 28800bps" 売上="98401" インダストリーID="GG119" インダストリー名="転売"/><row チャネルID="CC4" チャネル名="カタログ" プロダクトID="PP23" プロダクト名="PCMCIA ﾓﾃﾞﾑ/FAX 28800bps" 売上="20818" インダストリーID="GG120" インダストリー名="政府"/><row チャネルID="CC4" チャネル名="カタログ" プロダクトID="PP23" プロダクト名="PCMCIA ﾓﾃﾞﾑ/FAX 28800bps" 売上="982" インダストリーID="GG121" インダストリー名="教育"/><row チャネルID="CC4" チャネル名="カタログ" プロダクトID="PP24" プロダクト名="SIMM- 8MB PCMCIAIIｶｰﾄﾞ" 売上="50735" インダストリーID="GG113" インダストリー名="製造"/><row チャネルID="CC4" チャネル名="カタログ" プロダクトID="PP24" プロダクト名="SIMM- 8MB PCMCIAIIｶｰﾄﾞ" 売上="18848" インダストリーID="GG114" インダストリー名="機械"/><row チャネルID="CC4" チャネル名="カタログ" プロダクトID="PP24" プロダクト名="SIMM- 8MB PCMCIAIIｶｰﾄﾞ" 売上="43844" インダストリーID="GG115" インダストリー名="防衛"/><row チャネルID="CC4" チャネル名="カタログ" プロダクトID="PP24" プロダクト名="SIMM- 8MB PCMCIAIIｶｰﾄﾞ" 売上="90985" インダストリーID="GG116" インダストリー名="コンサルティング"/><row チャネルID="CC4" チャネル名="カタログ" プロダクトID="PP24" プロダクト名="SIMM- 8MB PCMCIAIIｶｰﾄﾞ" 売上="100433" インダストリーID="GG117" インダストリー名="ＳＩ"/><row チャネルID="CC4" チャネル名="カタログ" プロダクトID="PP24" プロダクト名="SIMM- 8MB PCMCIAIIｶｰﾄﾞ" 売上="21657" インダストリーID="GG118" インダストリー名="航空宇宙"/><row チャネルID="CC4" チャネル名="カタログ" プロダクトID="PP24" プロダクト名="SIMM- 8MB PCMCIAIIｶｰﾄﾞ" 売上="66425" インダストリーID="GG119" インダストリー名="転売"/><row チャネルID="CC4" チャネル名="カタログ" プロダクトID="PP24" プロダクト名="SIMM- 8MB PCMCIAIIｶｰﾄﾞ" 売上="16124" インダストリーID="GG120" インダストリー名="政府"/><row チャネルID="CC4" チャネル名="カタログ" プロダクトID="PP24" プロダクト名="SIMM- 8MB PCMCIAIIｶｰﾄﾞ" 売上="832" インダストリーID="GG121" インダストリー名="教育"/><row チャネルID="CC4" チャネル名="カタログ" プロダクトID="PP25" プロダクト名="SIMM- 16MB PCMCIAIIｶｰﾄﾞ" 売上="23894" インダストリーID="GG113" インダストリー名="製造"/><row チャネルID="CC4" チャネル名="カタログ" プロダクトID="PP25" プロダクト名="SIMM- 16MB PCMCIAIIｶｰﾄﾞ" 売上="13998" インダストリーID="GG114" インダストリー名="機械"/><row チャネルID="CC4" チャネル名="カタログ" プロダクトID="PP25" プロダクト名="SIMM- 16MB PCMCIAIIｶｰﾄﾞ" 売上="26636" インダストリーID="GG115" インダストリー名="防衛"/><row チャネルID="CC4" チャネル名="カタログ" プロダクトID="PP25" プロダクト名="SIMM- 16MB PCMCIAIIｶｰﾄﾞ" 売上="52371" インダストリーID="GG116" インダストリー名="コンサルティング"/><row チャネルID="CC4" チャネル名="カタログ" プロダクトID="PP25" プロダクト名="SIMM- 16MB PCMCIAIIｶｰﾄﾞ" 売上="56670" インダストリーID="GG117" インダストリー名="ＳＩ"/><row チャネルID="CC4" チャネル名="カタログ" プロダクトID="PP25" プロダクト名="SIMM- 16MB PCMCIAIIｶｰﾄﾞ" 売上="13338" インダストリーID="GG118" インダストリー名="航空宇宙"/><row チャネルID="CC4" チャネル名="カタログ" プロダクトID="PP25" プロダクト名="SIMM- 16MB PCMCIAIIｶｰﾄﾞ" 売上="47381" インダストリーID="GG119" インダストリー名="転売"/><row チャネルID="CC4" チャネル名="カタログ" プロダクトID="PP25" プロダクト名="SIMM- 16MB PCMCIAIIｶｰﾄﾞ" 売上="8732" インダストリーID="GG120" インダストリー名="政府"/><row チャネルID="CC4" チャネル名="カタログ" プロダクトID="PP25" プロダクト名="SIMM- 16MB PCMCIAIIｶｰﾄﾞ" 売上="468" インダストリーID="GG121" インダストリー名="教育"/><row チャネルID="CC4" チャネル名="カタログ" プロダクトID="PP26" プロダクト名="ﾏﾙﾁﾒﾃﾞｨｱ･ｽﾋﾟｰｶ" 売上="8956" インダストリーID="GG113" インダストリー名="製造"/><row チャネルID="CC4" チャネル名="カタログ" プロダクトID="PP26" プロダクト名="ﾏﾙﾁﾒﾃﾞｨｱ･ｽﾋﾟｰｶ" 売上="3282" インダストリーID="GG114" インダストリー名="機械"/><row チャネルID="CC4" チャネル名="カタログ" プロダクトID="PP26" プロダクト名="ﾏﾙﾁﾒﾃﾞｨｱ･ｽﾋﾟｰｶ" 売上="8848" インダストリーID="GG115" インダストリー名="防衛"/><row チャネルID="CC4" チャネル名="カタログ" プロダクトID="PP26" プロダクト名="ﾏﾙﾁﾒﾃﾞｨｱ･ｽﾋﾟｰｶ" 売上="14494" インダストリーID="GG116" インダストリー名="コンサルティング"/><row チャネルID="CC4" チャネル名="カタログ" プロダクトID="PP26" プロダクト名="ﾏﾙﾁﾒﾃﾞｨｱ･ｽﾋﾟｰｶ" 売上="15348" インダストリーID="GG117" インダストリー名="ＳＩ"/><row チャネルID="CC4" チャネル名="カタログ" プロダクトID="PP26" プロダクト名="ﾏﾙﾁﾒﾃﾞｨｱ･ｽﾋﾟｰｶ" 売上="4366" インダストリーID="GG118" インダストリー名="航空宇宙"/><row チャネルID="CC4" チャネル名="カタログ" プロダクトID="PP26" プロダクト名="ﾏﾙﾁﾒﾃﾞｨｱ･ｽﾋﾟｰｶ" 売上="12383" インダストリーID="GG119" インダストリー名="転売"/><row チャネルID="CC4" チャネル名="カタログ" プロダクトID="PP26" プロダクト名="ﾏﾙﾁﾒﾃﾞｨｱ･ｽﾋﾟｰｶ" 売上="2961" インダストリーID="GG120" インダストリー名="政府"/><row チャネルID="CC4" チャネル名="カタログ" プロダクトID="PP26" プロダクト名="ﾏﾙﾁﾒﾃﾞｨｱ･ｽﾋﾟｰｶ" 売上="98" インダストリーID="GG121" インダストリー名="教育"/><row チャネルID="CC4" チャネル名="カタログ" プロダクトID="PP27" プロダクト名="Unix/Windows 1ﾕｰｻﾞ･ﾊﾟｯｸ" 売上="45243" インダストリーID="GG113" インダストリー名="製造"/><row チャネルID="CC4" チャネル名="カタログ" プロダクトID="PP27" プロダクト名="Unix/Windows 1ﾕｰｻﾞ･ﾊﾟｯｸ" 売上="17853" インダストリーID="GG114" インダストリー名="機械"/><row チャネルID="CC4" チャネル名="カタログ" プロダクトID="PP27" プロダクト名="Unix/Windows 1ﾕｰｻﾞ･ﾊﾟｯｸ" 売上="48438" インダストリーID="GG115" インダストリー名="防衛"/><row チャネルID="CC4" チャネル名="カタログ" プロダクトID="PP27" プロダクト名="Unix/Windows 1ﾕｰｻﾞ･ﾊﾟｯｸ" 売上="81300" インダストリーID="GG116" インダストリー名="コンサルティング"/><row チャネルID="CC4" チャネル名="カタログ" プロダクトID="PP27" プロダクト名="Unix/Windows 1ﾕｰｻﾞ･ﾊﾟｯｸ" 売上="103465" インダストリーID="GG117" インダストリー名="ＳＩ"/><row チャネルID="CC4" チャネル名="カタログ" プロダクトID="PP27" プロダクト名="Unix/Windows 1ﾕｰｻﾞ･ﾊﾟｯｸ" 売上="22718" インダストリーID="GG118" インダストリー名="航空宇宙"/><row チャネルID="CC4" チャネル名="カタログ" プロダクトID="PP27" プロダクト名="Unix/Windows 1ﾕｰｻﾞ･ﾊﾟｯｸ" 売上="67398" インダストリーID="GG119" インダストリー名="転売"/><row チャネルID="CC4" チャネル名="カタログ" プロダクトID="PP27" プロダクト名="Unix/Windows 1ﾕｰｻﾞ･ﾊﾟｯｸ" 売上="15613" インダストリーID="GG120" インダストリー名="政府"/><row チャネルID="CC4" チャネル名="カタログ" プロダクトID="PP27" プロダクト名="Unix/Windows 1ﾕｰｻﾞ･ﾊﾟｯｸ" 売上="905" インダストリーID="GG121" インダストリー名="教育"/><row チャネルID="CC4" チャネル名="カタログ" プロダクトID="PP28" プロダクト名="Unix/Windows 5ﾕｰｻﾞ･ﾊﾟｯｸ" 売上="3592" インダストリーID="GG113" インダストリー名="製造"/><row チャネルID="CC4" チャネル名="カタログ" プロダクトID="PP28" プロダクト名="Unix/Windows 5ﾕｰｻﾞ･ﾊﾟｯｸ" 売上="1227" インダストリーID="GG114" インダストリー名="機械"/><row チャネルID="CC4" チャネル名="カタログ" プロダクトID="PP28" プロダクト名="Unix/Windows 5ﾕｰｻﾞ･ﾊﾟｯｸ" 売上="3386" インダストリーID="GG115" インダストリー名="防衛"/><row チャネルID="CC4" チャネル名="カタログ" プロダクトID="PP28" プロダクト名="Unix/Windows 5ﾕｰｻﾞ･ﾊﾟｯｸ" 売上="5474" インダストリーID="GG116" インダストリー名="コンサルティング"/><row チャネルID="CC4" チャネル名="カタログ" プロダクトID="PP28" プロダクト名="Unix/Windows 5ﾕｰｻﾞ･ﾊﾟｯｸ" 売上="6560" インダストリーID="GG117" インダストリー名="ＳＩ"/><row チャネルID="CC4" チャネル名="カタログ" プロダクトID="PP28" プロダクト名="Unix/Windows 5ﾕｰｻﾞ･ﾊﾟｯｸ" 売上="1109" インダストリーID="GG118" インダストリー名="航空宇宙"/><row チャネルID="CC4" チャネル名="カタログ" プロダクトID="PP28" プロダクト名="Unix/Windows 5ﾕｰｻﾞ･ﾊﾟｯｸ" 売上="5125" インダストリーID="GG119" インダストリー名="転売"/><row チャネルID="CC4" チャネル名="カタログ" プロダクトID="PP28" プロダクト名="Unix/Windows 5ﾕｰｻﾞ･ﾊﾟｯｸ" 売上="863" インダストリーID="GG120" インダストリー名="政府"/><row チャネルID="CC4" チャネル名="カタログ" プロダクトID="PP28" プロダクト名="Unix/Windows 5ﾕｰｻﾞ･ﾊﾟｯｸ" 売上="0" インダストリーID="GG121" インダストリー名="教育"/><row チャネルID="CC4" チャネル名="カタログ" プロダクトID="PP29" プロダクト名="マウス・パッド" 売上="465" インダストリーID="GG113" インダストリー名="製造"/><row チャネルID="CC4" チャネル名="カタログ" プロダクトID="PP29" プロダクト名="マウス・パッド" 売上="202" インダストリーID="GG114" インダストリー名="機械"/><row チャネルID="CC4" チャネル名="カタログ" プロダクトID="PP29" プロダクト名="マウス・パッド" 売上="528" インダストリーID="GG115" インダストリー名="防衛"/><row チャネルID="CC4" チャネル名="カタログ" プロダクトID="PP29" プロダクト名="マウス・パッド" 売上="1065" インダストリーID="GG116" インダストリー名="コンサルティング"/><row チャネルID="CC4" チャネル名="カタログ" プロダクトID="PP29" プロダクト名="マウス・パッド" 売上="926" インダストリーID="GG117" インダストリー名="ＳＩ"/><row チャネルID="CC4" チャネル名="カタログ" プロダクトID="PP29" プロダクト名="マウス・パッド" 売上="269" インダストリーID="GG118" インダストリー名="航空宇宙"/><row チャネルID="CC4" チャネル名="カタログ" プロダクトID="PP29" プロダクト名="マウス・パッド" 売上="776" インダストリーID="GG119" インダストリー名="転売"/><row チャネルID="CC4" チャネル名="カタログ" プロダクトID="PP29" プロダクト名="マウス・パッド" 売上="177" インダストリーID="GG120" インダストリー名="政府"/><row チャネルID="CC4" チャネル名="カタログ" プロダクトID="PP29" プロダクト名="マウス・パッド" 売上="9" インダストリーID="GG121" インダストリー名="教育"/><row チャネルID="CC4" チャネル名="カタログ" プロダクトID="PP30" プロダクト名="2.88MB  3.5 FD" 売上="34812" インダストリーID="GG113" インダストリー名="製造"/><row チャネルID="CC4" チャネル名="カタログ" プロダクトID="PP30" プロダクト名="2.88MB  3.5 FD" 売上="15666" インダストリーID="GG114" インダストリー名="機械"/><row チャネルID="CC4" チャネル名="カタログ" プロダクトID="PP30" プロダクト名="2.88MB  3.5 FD" 売上="33155" インダストリーID="GG115" インダストリー名="防衛"/><row チャネルID="CC4" チャネル名="カタログ" プロダクトID="PP30" プロダクト名="2.88MB  3.5 FD" 売上="76776" インダストリーID="GG116" インダストリー名="コンサルティング"/><row チャネルID="CC4" チャネル名="カタログ" プロダクトID="PP30" プロダクト名="2.88MB  3.5 FD" 売上="81790" インダストリーID="GG117" インダストリー名="ＳＩ"/><row チャネルID="CC4" チャネル名="カタログ" プロダクトID="PP30" プロダクト名="2.88MB  3.5 FD" 売上="13299" インダストリーID="GG118" インダストリー名="航空宇宙"/><row チャネルID="CC4" チャネル名="カタログ" プロダクトID="PP30" プロダクト名="2.88MB  3.5 FD" 売上="58626" インダストリーID="GG119" インダストリー名="転売"/><row チャネルID="CC4" チャネル名="カタログ" プロダクトID="PP30" プロダクト名="2.88MB  3.5 FD" 売上="12638" インダストリーID="GG120" インダストリー名="政府"/><row チャネルID="CC4" チャネル名="カタログ" プロダクトID="PP30" プロダクト名="2.88MB  3.5 FD" 売上="581" インダストリーID="GG121" インダストリー名="教育"/><row チャネルID="CC4" チャネル名="カタログ" プロダクトID="PP31" プロダクト名="ﾏﾙﾁﾒﾃﾞｨｱ･ｽﾋﾟｰｶ" 売上="8098" インダストリーID="GG113" インダストリー名="製造"/><row チャネルID="CC4" チャネル名="カタログ" プロダクトID="PP31" プロダクト名="ﾏﾙﾁﾒﾃﾞｨｱ･ｽﾋﾟｰｶ" 売上="3505" インダストリーID="GG114" インダストリー名="機械"/><row チャネルID="CC4" チャネル名="カタログ" プロダクトID="PP31" プロダクト名="ﾏﾙﾁﾒﾃﾞｨｱ･ｽﾋﾟｰｶ" 売上="7030" インダストリーID="GG115" インダストリー名="防衛"/><row チャネルID="CC4" チャネル名="カタログ" プロダクトID="PP31" プロダクト名="ﾏﾙﾁﾒﾃﾞｨｱ･ｽﾋﾟｰｶ" 売上="14559" インダストリーID="GG116" インダストリー名="コンサルティング"/><row チャネルID="CC4" チャネル名="カタログ" プロダクトID="PP31" プロダクト名="ﾏﾙﾁﾒﾃﾞｨｱ･ｽﾋﾟｰｶ" 売上="15476" インダストリーID="GG117" インダストリー名="ＳＩ"/><row チャネルID="CC4" チャネル名="カタログ" プロダクトID="PP31" プロダクト名="ﾏﾙﾁﾒﾃﾞｨｱ･ｽﾋﾟｰｶ" 売上="5460" インダストリーID="GG118" インダストリー名="航空宇宙"/><row チャネルID="CC4" チャネル名="カタログ" プロダクトID="PP31" プロダクト名="ﾏﾙﾁﾒﾃﾞｨｱ･ｽﾋﾟｰｶ" 売上="11701" インダストリーID="GG119" インダストリー名="転売"/><row チャネルID="CC4" チャネル名="カタログ" プロダクトID="PP31" プロダクト名="ﾏﾙﾁﾒﾃﾞｨｱ･ｽﾋﾟｰｶ" 売上="2378" インダストリーID="GG120" インダストリー名="政府"/><row チャネルID="CC4" チャネル名="カタログ" プロダクトID="PP31" プロダクト名="ﾏﾙﾁﾒﾃﾞｨｱ･ｽﾋﾟｰｶ" 売上="122" インダストリーID="GG121" インダストリー名="教育"/><row チャネルID="CC4" チャネル名="カタログ" プロダクトID="PP32" プロダクト名="PCMCIA ﾓﾃﾞﾑ/FAX 19200bps" 売上="6017" インダストリーID="GG113" インダストリー名="製造"/><row チャネルID="CC4" チャネル名="カタログ" プロダクトID="PP32" プロダクト名="PCMCIA ﾓﾃﾞﾑ/FAX 19200bps" 売上="2329" インダストリーID="GG114" インダストリー名="機械"/><row チャネルID="CC4" チャネル名="カタログ" プロダクトID="PP32" プロダクト名="PCMCIA ﾓﾃﾞﾑ/FAX 19200bps" 売上="7457" インダストリーID="GG115" インダストリー名="防衛"/><row チャネルID="CC4" チャネル名="カタログ" プロダクトID="PP32" プロダクト名="PCMCIA ﾓﾃﾞﾑ/FAX 19200bps" 売上="12094" インダストリーID="GG116" インダストリー名="コンサルティング"/><row チャネルID="CC4" チャネル名="カタログ" プロダクトID="PP32" プロダクト名="PCMCIA ﾓﾃﾞﾑ/FAX 19200bps" 売上="12816" インダストリーID="GG117" インダストリー名="ＳＩ"/><row チャネルID="CC4" チャネル名="カタログ" プロダクトID="PP32" プロダクト名="PCMCIA ﾓﾃﾞﾑ/FAX 19200bps" 売上="2726" インダストリーID="GG118" インダストリー名="航空宇宙"/><row チャネルID="CC4" チャネル名="カタログ" プロダクトID="PP32" プロダクト名="PCMCIA ﾓﾃﾞﾑ/FAX 19200bps" 売上="8690" インダストリーID="GG119" インダストリー名="転売"/><row チャネルID="CC4" チャネル名="カタログ" プロダクトID="PP32" プロダクト名="PCMCIA ﾓﾃﾞﾑ/FAX 19200bps" 売上="2046" インダストリーID="GG120" インダストリー名="政府"/><row チャネルID="CC4" チャネル名="カタログ" プロダクトID="PP32" プロダクト名="PCMCIA ﾓﾃﾞﾑ/FAX 19200bps" 売上="82" インダストリーID="GG121" インダストリー名="教育"/><row チャネルID="CC5" チャネル名="Webカタログ" プロダクトID="PP11" プロダクト名="Envoy ｽﾀﾝﾀﾞｰﾄﾞ" 売上="0" インダストリーID="GG113" インダストリー名="製造"/><row チャネルID="CC5" チャネル名="Webカタログ" プロダクトID="PP11" プロダクト名="Envoy ｽﾀﾝﾀﾞｰﾄﾞ" 売上="0" インダストリーID="GG114" インダストリー名="機械"/><row チャネルID="CC5" チャネル名="Webカタログ" プロダクトID="PP11" プロダクト名="Envoy ｽﾀﾝﾀﾞｰﾄﾞ" 売上="0" インダストリーID="GG115" インダストリー名="防衛"/><row チャネルID="CC5" チャネル名="Webカタログ" プロダクトID="PP11" プロダクト名="Envoy ｽﾀﾝﾀﾞｰﾄﾞ" 売上="0" インダストリーID="GG116" インダストリー名="コンサルティング"/><row チャネルID="CC5" チャネル名="Webカタログ" プロダクトID="PP11" プロダクト名="Envoy ｽﾀﾝﾀﾞｰﾄﾞ" 売上="0" インダストリーID="GG117" インダストリー名="ＳＩ"/><row チャネルID="CC5" チャネル名="Webカタログ" プロダクトID="PP11" プロダクト名="Envoy ｽﾀﾝﾀﾞｰﾄﾞ" 売上="0" インダストリーID="GG118" インダストリー名="航空宇宙"/><row チャネルID="CC5" チャネル名="Webカタログ" プロダクトID="PP11" プロダクト名="Envoy ｽﾀﾝﾀﾞｰﾄﾞ" 売上="0" インダストリーID="GG119" インダストリー名="転売"/><row チャネルID="CC5" チャネル名="Webカタログ" プロダクトID="PP11" プロダクト名="Envoy ｽﾀﾝﾀﾞｰﾄﾞ" 売上="0" インダストリーID="GG120" インダストリー名="政府"/><row チャネルID="CC5" チャネル名="Webカタログ" プロダクトID="PP11" プロダクト名="Envoy ｽﾀﾝﾀﾞｰﾄﾞ" 売上="0" インダストリーID="GG121" インダストリー名="教育"/><row チャネルID="CC5" チャネル名="Webカタログ" プロダクトID="PP12" プロダクト名="Envoy ｴｸﾞｾﾞｸﾃｨﾌﾞ" 売上="0" インダストリーID="GG113" インダストリー名="製造"/><row チャネルID="CC5" チャネル名="Webカタログ" プロダクトID="PP12" プロダクト名="Envoy ｴｸﾞｾﾞｸﾃｨﾌﾞ" 売上="0" インダストリーID="GG114" インダストリー名="機械"/><row チャネルID="CC5" チャネル名="Webカタログ" プロダクトID="PP12" プロダクト名="Envoy ｴｸﾞｾﾞｸﾃｨﾌﾞ" 売上="0" インダストリーID="GG115" インダストリー名="防衛"/><row チャネルID="CC5" チャネル名="Webカタログ" プロダクトID="PP12" プロダクト名="Envoy ｴｸﾞｾﾞｸﾃｨﾌﾞ" 売上="0" インダストリーID="GG116" インダストリー名="コンサルティング"/><row チャネルID="CC5" チャネル名="Webカタログ" プロダクトID="PP12" プロダクト名="Envoy ｴｸﾞｾﾞｸﾃｨﾌﾞ" 売上="0" インダストリーID="GG117" インダストリー名="ＳＩ"/><row チャネルID="CC5" チャネル名="Webカタログ" プロダクトID="PP12" プロダクト名="Envoy ｴｸﾞｾﾞｸﾃｨﾌﾞ" 売上="0" インダストリーID="GG118" インダストリー名="航空宇宙"/><row チャネルID="CC5" チャネル名="Webカタログ" プロダクトID="PP12" プロダクト名="Envoy ｴｸﾞｾﾞｸﾃｨﾌﾞ" 売上="0" インダストリーID="GG119" インダストリー名="転売"/><row チャネルID="CC5" チャネル名="Webカタログ" プロダクトID="PP12" プロダクト名="Envoy ｴｸﾞｾﾞｸﾃｨﾌﾞ" 売上="0" インダストリーID="GG120" インダストリー名="政府"/><row チャネルID="CC5" チャネル名="Webカタログ" プロダクトID="PP12" プロダクト名="Envoy ｴｸﾞｾﾞｸﾃｨﾌﾞ" 売上="0" インダストリーID="GG121" インダストリー名="教育"/><row チャネルID="CC5" チャネル名="Webカタログ" プロダクトID="PP13" プロダクト名="Envoy ｱﾝﾊﾞｻﾀﾞｰ" 売上="0" インダストリーID="GG113" インダストリー名="製造"/><row チャネルID="CC5" チャネル名="Webカタログ" プロダクトID="PP13" プロダクト名="Envoy ｱﾝﾊﾞｻﾀﾞｰ" 売上="0" インダストリーID="GG114" インダストリー名="機械"/><row チャネルID="CC5" チャネル名="Webカタログ" プロダクトID="PP13" プロダクト名="Envoy ｱﾝﾊﾞｻﾀﾞｰ" 売上="0" インダストリーID="GG115" インダストリー名="防衛"/><row チャネルID="CC5" チャネル名="Webカタログ" プロダクトID="PP13" プロダクト名="Envoy ｱﾝﾊﾞｻﾀﾞｰ" 売上="0" インダストリーID="GG116" インダストリー名="コンサルティング"/><row チャネルID="CC5" チャネル名="Webカタログ" プロダクトID="PP13" プロダクト名="Envoy ｱﾝﾊﾞｻﾀﾞｰ" 売上="0" インダストリーID="GG117" インダストリー名="ＳＩ"/><row チャネルID="CC5" チャネル名="Webカタログ" プロダクトID="PP13" プロダクト名="Envoy ｱﾝﾊﾞｻﾀﾞｰ" 売上="0" インダストリーID="GG118" インダストリー名="航空宇宙"/><row チャネルID="CC5" チャネル名="Webカタログ" プロダクトID="PP13" プロダクト名="Envoy ｱﾝﾊﾞｻﾀﾞｰ" 売上="0" インダストリーID="GG119" インダストリー名="転売"/><row チャネルID="CC5" チャネル名="Webカタログ" プロダクトID="PP13" プロダクト名="Envoy ｱﾝﾊﾞｻﾀﾞｰ" 売上="0" インダストリーID="GG120" インダストリー名="政府"/><row チャネルID="CC5" チャネル名="Webカタログ" プロダクトID="PP13" プロダクト名="Envoy ｱﾝﾊﾞｻﾀﾞｰ" 売上="0" インダストリーID="GG121" インダストリー名="教育"/><row チャネルID="CC5" チャネル名="Webカタログ" プロダクトID="PP14" プロダクト名="Sentinel ｽﾀﾝﾀﾞｰﾄﾞ" 売上="0" インダストリーID="GG113" インダストリー名="製造"/><row チャネルID="CC5" チャネル名="Webカタログ" プロダクトID="PP14" プロダクト名="Sentinel ｽﾀﾝﾀﾞｰﾄﾞ" 売上="0" インダストリーID="GG114" インダストリー名="機械"/><row チャネルID="CC5" チャネル名="Webカタログ" プロダクトID="PP14" プロダクト名="Sentinel ｽﾀﾝﾀﾞｰﾄﾞ" 売上="0" インダストリーID="GG115" インダストリー名="防衛"/><row チャネルID="CC5" チャネル名="Webカタログ" プロダクトID="PP14" プロダクト名="Sentinel ｽﾀﾝﾀﾞｰﾄﾞ" 売上="0" インダストリーID="GG116" インダストリー名="コンサルティング"/><row チャネルID="CC5" チャネル名="Webカタログ" プロダクトID="PP14" プロダクト名="Sentinel ｽﾀﾝﾀﾞｰﾄﾞ" 売上="0" インダストリーID="GG117" インダストリー名="ＳＩ"/><row チャネルID="CC5" チャネル名="Webカタログ" プロダクトID="PP14" プロダクト名="Sentinel ｽﾀﾝﾀﾞｰﾄﾞ" 売上="0" インダストリーID="GG118" インダストリー名="航空宇宙"/><row チャネルID="CC5" チャネル名="Webカタログ" プロダクトID="PP14" プロダクト名="Sentinel ｽﾀﾝﾀﾞｰﾄﾞ" 売上="0" インダストリーID="GG119" インダストリー名="転売"/><row チャネルID="CC5" チャネル名="Webカタログ" プロダクトID="PP14" プロダクト名="Sentinel ｽﾀﾝﾀﾞｰﾄﾞ" 売上="0" インダストリーID="GG120" インダストリー名="政府"/><row チャネルID="CC5" チャネル名="Webカタログ" プロダクトID="PP14" プロダクト名="Sentinel ｽﾀﾝﾀﾞｰﾄﾞ" 売上="0" インダストリーID="GG121" インダストリー名="教育"/><row チャネルID="CC5" チャネル名="Webカタログ" プロダクトID="PP15" プロダクト名="Sentinel ﾌｧｲﾅﾝｼｬﾙ" 売上="0" インダストリーID="GG113" インダストリー名="製造"/><row チャネルID="CC5" チャネル名="Webカタログ" プロダクトID="PP15" プロダクト名="Sentinel ﾌｧｲﾅﾝｼｬﾙ" 売上="0" インダストリーID="GG114" インダストリー名="機械"/><row チャネルID="CC5" チャネル名="Webカタログ" プロダクトID="PP15" プロダクト名="Sentinel ﾌｧｲﾅﾝｼｬﾙ" 売上="0" インダストリーID="GG115" インダストリー名="防衛"/><row チャネルID="CC5" チャネル名="Webカタログ" プロダクトID="PP15" プロダクト名="Sentinel ﾌｧｲﾅﾝｼｬﾙ" 売上="0" インダストリーID="GG116" インダストリー名="コンサルティング"/><row チャネルID="CC5" チャネル名="Webカタログ" プロダクトID="PP15" プロダクト名="Sentinel ﾌｧｲﾅﾝｼｬﾙ" 売上="0" インダストリーID="GG117" インダストリー名="ＳＩ"/><row チャネルID="CC5" チャネル名="Webカタログ" プロダクトID="PP15" プロダクト名="Sentinel ﾌｧｲﾅﾝｼｬﾙ" 売上="0" インダストリーID="GG118" インダストリー名="航空宇宙"/><row チャネルID="CC5" チャネル名="Webカタログ" プロダクトID="PP15" プロダクト名="Sentinel ﾌｧｲﾅﾝｼｬﾙ" 売上="0" インダストリーID="GG119" インダストリー名="転売"/><row チャネルID="CC5" チャネル名="Webカタログ" プロダクトID="PP15" プロダクト名="Sentinel ﾌｧｲﾅﾝｼｬﾙ" 売上="0" インダストリーID="GG120" インダストリー名="政府"/><row チャネルID="CC5" チャネル名="Webカタログ" プロダクトID="PP15" プロダクト名="Sentinel ﾌｧｲﾅﾝｼｬﾙ" 売上="0" インダストリーID="GG121" インダストリー名="教育"/><row チャネルID="CC5" チャネル名="Webカタログ" プロダクトID="PP16" プロダクト名="Sentinel ﾏﾙﾁﾒﾃﾞｨｱ" 売上="0" インダストリーID="GG113" インダストリー名="製造"/><row チャネルID="CC5" チャネル名="Webカタログ" プロダクトID="PP16" プロダクト名="Sentinel ﾏﾙﾁﾒﾃﾞｨｱ" 売上="0" インダストリーID="GG114" インダストリー名="機械"/><row チャネルID="CC5" チャネル名="Webカタログ" プロダクトID="PP16" プロダクト名="Sentinel ﾏﾙﾁﾒﾃﾞｨｱ" 売上="0" インダストリーID="GG115" インダストリー名="防衛"/><row チャネルID="CC5" チャネル名="Webカタログ" プロダクトID="PP16" プロダクト名="Sentinel ﾏﾙﾁﾒﾃﾞｨｱ" 売上="0" インダストリーID="GG116" インダストリー名="コンサルティング"/><row チャネルID="CC5" チャネル名="Webカタログ" プロダクトID="PP16" プロダクト名="Sentinel ﾏﾙﾁﾒﾃﾞｨｱ" 売上="0" インダストリーID="GG117" インダストリー名="ＳＩ"/><row チャネルID="CC5" チャネル名="Webカタログ" プロダクトID="PP16" プロダクト名="Sentinel ﾏﾙﾁﾒﾃﾞｨｱ" 売上="0" インダストリーID="GG118" インダストリー名="航空宇宙"/><row チャネルID="CC5" チャネル名="Webカタログ" プロダクトID="PP16" プロダクト名="Sentinel ﾏﾙﾁﾒﾃﾞｨｱ" 売上="0" インダストリーID="GG119" インダストリー名="転売"/><row チャネルID="CC5" チャネル名="Webカタログ" プロダクトID="PP16" プロダクト名="Sentinel ﾏﾙﾁﾒﾃﾞｨｱ" 売上="0" インダストリーID="GG120" インダストリー名="政府"/><row チャネルID="CC5" チャネル名="Webカタログ" プロダクトID="PP16" プロダクト名="Sentinel ﾏﾙﾁﾒﾃﾞｨｱ" 売上="0" インダストリーID="GG121" インダストリー名="教育"/><row チャネルID="CC5" チャネル名="Webカタログ" プロダクトID="PP17" プロダクト名="ＯＳﾄﾞｷｭﾒﾝﾄ一式" 売上="0" インダストリーID="GG113" インダストリー名="製造"/><row チャネルID="CC5" チャネル名="Webカタログ" プロダクトID="PP17" プロダクト名="ＯＳﾄﾞｷｭﾒﾝﾄ一式" 売上="0" インダストリーID="GG114" インダストリー名="機械"/><row チャネルID="CC5" チャネル名="Webカタログ" プロダクトID="PP17" プロダクト名="ＯＳﾄﾞｷｭﾒﾝﾄ一式" 売上="0" インダストリーID="GG115" インダストリー名="防衛"/><row チャネルID="CC5" チャネル名="Webカタログ" プロダクトID="PP17" プロダクト名="ＯＳﾄﾞｷｭﾒﾝﾄ一式" 売上="0" インダストリーID="GG116" インダストリー名="コンサルティング"/><row チャネルID="CC5" チャネル名="Webカタログ" プロダクトID="PP17" プロダクト名="ＯＳﾄﾞｷｭﾒﾝﾄ一式" 売上="0" インダストリーID="GG117" インダストリー名="ＳＩ"/><row チャネルID="CC5" チャネル名="Webカタログ" プロダクトID="PP17" プロダクト名="ＯＳﾄﾞｷｭﾒﾝﾄ一式" 売上="0" インダストリーID="GG118" インダストリー名="航空宇宙"/><row チャネルID="CC5" チャネル名="Webカタログ" プロダクトID="PP17" プロダクト名="ＯＳﾄﾞｷｭﾒﾝﾄ一式" 売上="0" インダストリーID="GG119" インダストリー名="転売"/><row チャネルID="CC5" チャネル名="Webカタログ" プロダクトID="PP17" プロダクト名="ＯＳﾄﾞｷｭﾒﾝﾄ一式" 売上="0" インダストリーID="GG120" インダストリー名="政府"/><row チャネルID="CC5" チャネル名="Webカタログ" プロダクトID="PP17" プロダクト名="ＯＳﾄﾞｷｭﾒﾝﾄ一式" 売上="0" インダストリーID="GG121" インダストリー名="教育"/><row チャネルID="CC5" チャネル名="Webカタログ" プロダクトID="PP18" プロダクト名="ﾉｰﾄPC ｷｬﾘﾝｸﾞ･ｹｰｽ" 売上="0" インダストリーID="GG113" インダストリー名="製造"/><row チャネルID="CC5" チャネル名="Webカタログ" プロダクトID="PP18" プロダクト名="ﾉｰﾄPC ｷｬﾘﾝｸﾞ･ｹｰｽ" 売上="0" インダストリーID="GG114" インダストリー名="機械"/><row チャネルID="CC5" チャネル名="Webカタログ" プロダクトID="PP18" プロダクト名="ﾉｰﾄPC ｷｬﾘﾝｸﾞ･ｹｰｽ" 売上="0" インダストリーID="GG115" インダストリー名="防衛"/><row チャネルID="CC5" チャネル名="Webカタログ" プロダクトID="PP18" プロダクト名="ﾉｰﾄPC ｷｬﾘﾝｸﾞ･ｹｰｽ" 売上="0" インダストリーID="GG116" インダストリー名="コンサルティング"/><row チャネルID="CC5" チャネル名="Webカタログ" プロダクトID="PP18" プロダクト名="ﾉｰﾄPC ｷｬﾘﾝｸﾞ･ｹｰｽ" 売上="0" インダストリーID="GG117" インダストリー名="ＳＩ"/><row チャネルID="CC5" チャネル名="Webカタログ" プロダクトID="PP18" プロダクト名="ﾉｰﾄPC ｷｬﾘﾝｸﾞ･ｹｰｽ" 売上="0" インダストリーID="GG118" インダストリー名="航空宇宙"/><row チャネルID="CC5" チャネル名="Webカタログ" プロダクトID="PP18" プロダクト名="ﾉｰﾄPC ｷｬﾘﾝｸﾞ･ｹｰｽ" 売上="0" インダストリーID="GG119" インダストリー名="転売"/><row チャネルID="CC5" チャネル名="Webカタログ" プロダクトID="PP18" プロダクト名="ﾉｰﾄPC ｷｬﾘﾝｸﾞ･ｹｰｽ" 売上="0" インダストリーID="GG120" インダストリー名="政府"/><row チャネルID="CC5" チャネル名="Webカタログ" プロダクトID="PP18" プロダクト名="ﾉｰﾄPC ｷｬﾘﾝｸﾞ･ｹｰｽ" 売上="0" インダストリーID="GG121" インダストリー名="教育"/><row チャネルID="CC5" チャネル名="Webカタログ" プロダクトID="PP19" プロダクト名="ﾓﾆﾀｰ 15 Super VGA" 売上="0" インダストリーID="GG113" インダストリー名="製造"/><row チャネルID="CC5" チャネル名="Webカタログ" プロダクトID="PP19" プロダクト名="ﾓﾆﾀｰ 15 Super VGA" 売上="0" インダストリーID="GG114" インダストリー名="機械"/><row チャネルID="CC5" チャネル名="Webカタログ" プロダクトID="PP19" プロダクト名="ﾓﾆﾀｰ 15 Super VGA" 売上="0" インダストリーID="GG115" インダストリー名="防衛"/><row チャネルID="CC5" チャネル名="Webカタログ" プロダクトID="PP19" プロダクト名="ﾓﾆﾀｰ 15 Super VGA" 売上="0" インダストリーID="GG116" インダストリー名="コンサルティング"/><row チャネルID="CC5" チャネル名="Webカタログ" プロダクトID="PP19" プロダクト名="ﾓﾆﾀｰ 15 Super VGA" 売上="0" インダストリーID="GG117" インダストリー名="ＳＩ"/><row チャネルID="CC5" チャネル名="Webカタログ" プロダクトID="PP19" プロダクト名="ﾓﾆﾀｰ 15 Super VGA" 売上="0" インダストリーID="GG118" インダストリー名="航空宇宙"/><row チャネルID="CC5" チャネル名="Webカタログ" プロダクトID="PP19" プロダクト名="ﾓﾆﾀｰ 15 Super VGA" 売上="0" インダストリーID="GG119" インダストリー名="転売"/><row チャネルID="CC5" チャネル名="Webカタログ" プロダクトID="PP19" プロダクト名="ﾓﾆﾀｰ 15 Super VGA" 売上="0" インダストリーID="GG120" インダストリー名="政府"/><row チャネルID="CC5" チャネル名="Webカタログ" プロダクトID="PP19" プロダクト名="ﾓﾆﾀｰ 15 Super VGA" 売上="0" インダストリーID="GG121" インダストリー名="教育"/><row チャネルID="CC5" チャネル名="Webカタログ" プロダクトID="PP20" プロダクト名="ﾓﾆﾀｰ 19 Super VGA" 売上="0" インダストリーID="GG113" インダストリー名="製造"/><row チャネルID="CC5" チャネル名="Webカタログ" プロダクトID="PP20" プロダクト名="ﾓﾆﾀｰ 19 Super VGA" 売上="0" インダストリーID="GG114" インダストリー名="機械"/><row チャネルID="CC5" チャネル名="Webカタログ" プロダクトID="PP20" プロダクト名="ﾓﾆﾀｰ 19 Super VGA" 売上="0" インダストリーID="GG115" インダストリー名="防衛"/><row チャネルID="CC5" チャネル名="Webカタログ" プロダクトID="PP20" プロダクト名="ﾓﾆﾀｰ 19 Super VGA" 売上="0" インダストリーID="GG116" インダストリー名="コンサルティング"/><row チャネルID="CC5" チャネル名="Webカタログ" プロダクトID="PP20" プロダクト名="ﾓﾆﾀｰ 19 Super VGA" 売上="0" インダストリーID="GG117" インダストリー名="ＳＩ"/><row チャネルID="CC5" チャネル名="Webカタログ" プロダクトID="PP20" プロダクト名="ﾓﾆﾀｰ 19 Super VGA" 売上="0" インダストリーID="GG118" インダストリー名="航空宇宙"/><row チャネルID="CC5" チャネル名="Webカタログ" プロダクトID="PP20" プロダクト名="ﾓﾆﾀｰ 19 Super VGA" 売上="0" インダストリーID="GG119" インダストリー名="転売"/><row チャネルID="CC5" チャネル名="Webカタログ" プロダクトID="PP20" プロダクト名="ﾓﾆﾀｰ 19 Super VGA" 売上="0" インダストリーID="GG120" インダストリー名="政府"/><row チャネルID="CC5" チャネル名="Webカタログ" プロダクトID="PP20" プロダクト名="ﾓﾆﾀｰ 19 Super VGA" 売上="0" インダストリーID="GG121" インダストリー名="教育"/><row チャネルID="CC5" チャネル名="Webカタログ" プロダクトID="PP21" プロダクト名="Envoy 内蔵キーボード" 売上="0" インダストリーID="GG113" インダストリー名="製造"/><row チャネルID="CC5" チャネル名="Webカタログ" プロダクトID="PP21" プロダクト名="Envoy 内蔵キーボード" 売上="0" インダストリーID="GG114" インダストリー名="機械"/><row チャネルID="CC5" チャネル名="Webカタログ" プロダクトID="PP21" プロダクト名="Envoy 内蔵キーボード" 売上="0" インダストリーID="GG115" インダストリー名="防衛"/><row チャネルID="CC5" チャネル名="Webカタログ" プロダクトID="PP21" プロダクト名="Envoy 内蔵キーボード" 売上="0" インダストリーID="GG116" インダストリー名="コンサルティング"/><row チャネルID="CC5" チャネル名="Webカタログ" プロダクトID="PP21" プロダクト名="Envoy 内蔵キーボード" 売上="0" インダストリーID="GG117" インダストリー名="ＳＩ"/><row チャネルID="CC5" チャネル名="Webカタログ" プロダクトID="PP21" プロダクト名="Envoy 内蔵キーボード" 売上="0" インダストリーID="GG118" インダストリー名="航空宇宙"/><row チャネルID="CC5" チャネル名="Webカタログ" プロダクトID="PP21" プロダクト名="Envoy 内蔵キーボード" 売上="0" インダストリーID="GG119" インダストリー名="転売"/><row チャネルID="CC5" チャネル名="Webカタログ" プロダクトID="PP21" プロダクト名="Envoy 内蔵キーボード" 売上="0" インダストリーID="GG120" インダストリー名="政府"/><row チャネルID="CC5" チャネル名="Webカタログ" プロダクトID="PP21" プロダクト名="Envoy 内蔵キーボード" 売上="0" インダストリーID="GG121" インダストリー名="教育"/><row チャネルID="CC5" チャネル名="Webカタログ" プロダクトID="PP22" プロダクト名="外付け 101キーボード" 売上="0" インダストリーID="GG113" インダストリー名="製造"/><row チャネルID="CC5" チャネル名="Webカタログ" プロダクトID="PP22" プロダクト名="外付け 101キーボード" 売上="0" インダストリーID="GG114" インダストリー名="機械"/><row チャネルID="CC5" チャネル名="Webカタログ" プロダクトID="PP22" プロダクト名="外付け 101キーボード" 売上="0" インダストリーID="GG115" インダストリー名="防衛"/><row チャネルID="CC5" チャネル名="Webカタログ" プロダクトID="PP22" プロダクト名="外付け 101キーボード" 売上="0" インダストリーID="GG116" インダストリー名="コンサルティング"/><row チャネルID="CC5" チャネル名="Webカタログ" プロダクトID="PP22" プロダクト名="外付け 101キーボード" 売上="0" インダストリーID="GG117" インダストリー名="ＳＩ"/><row チャネルID="CC5" チャネル名="Webカタログ" プロダクトID="PP22" プロダクト名="外付け 101キーボード" 売上="0" インダストリーID="GG118" インダストリー名="航空宇宙"/><row チャネルID="CC5" チャネル名="Webカタログ" プロダクトID="PP22" プロダクト名="外付け 101キーボード" 売上="0" インダストリーID="GG119" インダストリー名="転売"/><row チャネルID="CC5" チャネル名="Webカタログ" プロダクトID="PP22" プロダクト名="外付け 101キーボード" 売上="0" インダストリーID="GG120" インダストリー名="政府"/><row チャネルID="CC5" チャネル名="Webカタログ" プロダクトID="PP22" プロダクト名="外付け 101キーボード" 売上="0" インダストリーID="GG121" インダストリー名="教育"/><row チャネルID="CC5" チャネル名="Webカタログ" プロダクトID="PP23" プロダクト名="PCMCIA ﾓﾃﾞﾑ/FAX 28800bps" 売上="0" インダストリーID="GG113" インダストリー名="製造"/><row チャネルID="CC5" チャネル名="Webカタログ" プロダクトID="PP23" プロダクト名="PCMCIA ﾓﾃﾞﾑ/FAX 28800bps" 売上="0" インダストリーID="GG114" インダストリー名="機械"/><row チャネルID="CC5" チャネル名="Webカタログ" プロダクトID="PP23" プロダクト名="PCMCIA ﾓﾃﾞﾑ/FAX 28800bps" 売上="0" インダストリーID="GG115" インダストリー名="防衛"/><row チャネルID="CC5" チャネル名="Webカタログ" プロダクトID="PP23" プロダクト名="PCMCIA ﾓﾃﾞﾑ/FAX 28800bps" 売上="0" インダストリーID="GG116" インダストリー名="コンサルティング"/><row チャネルID="CC5" チャネル名="Webカタログ" プロダクトID="PP23" プロダクト名="PCMCIA ﾓﾃﾞﾑ/FAX 28800bps" 売上="0" インダストリーID="GG117" インダストリー名="ＳＩ"/><row チャネルID="CC5" チャネル名="Webカタログ" プロダクトID="PP23" プロダクト名="PCMCIA ﾓﾃﾞﾑ/FAX 28800bps" 売上="0" インダストリーID="GG118" インダストリー名="航空宇宙"/><row チャネルID="CC5" チャネル名="Webカタログ" プロダクトID="PP23" プロダクト名="PCMCIA ﾓﾃﾞﾑ/FAX 28800bps" 売上="0" インダストリーID="GG119" インダストリー名="転売"/><row チャネルID="CC5" チャネル名="Webカタログ" プロダクトID="PP23" プロダクト名="PCMCIA ﾓﾃﾞﾑ/FAX 28800bps" 売上="0" インダストリーID="GG120" インダストリー名="政府"/><row チャネルID="CC5" チャネル名="Webカタログ" プロダクトID="PP23" プロダクト名="PCMCIA ﾓﾃﾞﾑ/FAX 28800bps" 売上="0" インダストリーID="GG121" インダストリー名="教育"/><row チャネルID="CC5" チャネル名="Webカタログ" プロダクトID="PP24" プロダクト名="SIMM- 8MB PCMCIAIIｶｰﾄﾞ" 売上="0" インダストリーID="GG113" インダストリー名="製造"/><row チャネルID="CC5" チャネル名="Webカタログ" プロダクトID="PP24" プロダクト名="SIMM- 8MB PCMCIAIIｶｰﾄﾞ" 売上="0" インダストリーID="GG114" インダストリー名="機械"/><row チャネルID="CC5" チャネル名="Webカタログ" プロダクトID="PP24" プロダクト名="SIMM- 8MB PCMCIAIIｶｰﾄﾞ" 売上="0" インダストリーID="GG115" インダストリー名="防衛"/><row チャネルID="CC5" チャネル名="Webカタログ" プロダクトID="PP24" プロダクト名="SIMM- 8MB PCMCIAIIｶｰﾄﾞ" 売上="0" インダストリーID="GG116" インダストリー名="コンサルティング"/><row チャネルID="CC5" チャネル名="Webカタログ" プロダクトID="PP24" プロダクト名="SIMM- 8MB PCMCIAIIｶｰﾄﾞ" 売上="0" インダストリーID="GG117" インダストリー名="ＳＩ"/><row チャネルID="CC5" チャネル名="Webカタログ" プロダクトID="PP24" プロダクト名="SIMM- 8MB PCMCIAIIｶｰﾄﾞ" 売上="0" インダストリーID="GG118" インダストリー名="航空宇宙"/><row チャネルID="CC5" チャネル名="Webカタログ" プロダクトID="PP24" プロダクト名="SIMM- 8MB PCMCIAIIｶｰﾄﾞ" 売上="0" インダストリーID="GG119" インダストリー名="転売"/><row チャネルID="CC5" チャネル名="Webカタログ" プロダクトID="PP24" プロダクト名="SIMM- 8MB PCMCIAIIｶｰﾄﾞ" 売上="0" インダストリーID="GG120" インダストリー名="政府"/><row チャネルID="CC5" チャネル名="Webカタログ" プロダクトID="PP24" プロダクト名="SIMM- 8MB PCMCIAIIｶｰﾄﾞ" 売上="0" インダストリーID="GG121" インダストリー名="教育"/><row チャネルID="CC5" チャネル名="Webカタログ" プロダクトID="PP25" プロダクト名="SIMM- 16MB PCMCIAIIｶｰﾄﾞ" 売上="0" インダストリーID="GG113" インダストリー名="製造"/><row チャネルID="CC5" チャネル名="Webカタログ" プロダクトID="PP25" プロダクト名="SIMM- 16MB PCMCIAIIｶｰﾄﾞ" 売上="0" インダストリーID="GG114" インダストリー名="機械"/><row チャネルID="CC5" チャネル名="Webカタログ" プロダクトID="PP25" プロダクト名="SIMM- 16MB PCMCIAIIｶｰﾄﾞ" 売上="0" インダストリーID="GG115" インダストリー名="防衛"/><row チャネルID="CC5" チャネル名="Webカタログ" プロダクトID="PP25" プロダクト名="SIMM- 16MB PCMCIAIIｶｰﾄﾞ" 売上="0" インダストリーID="GG116" インダストリー名="コンサルティング"/><row チャネルID="CC5" チャネル名="Webカタログ" プロダクトID="PP25" プロダクト名="SIMM- 16MB PCMCIAIIｶｰﾄﾞ" 売上="0" インダストリーID="GG117" インダストリー名="ＳＩ"/><row チャネルID="CC5" チャネル名="Webカタログ" プロダクトID="PP25" プロダクト名="SIMM- 16MB PCMCIAIIｶｰﾄﾞ" 売上="0" インダストリーID="GG118" インダストリー名="航空宇宙"/><row チャネルID="CC5" チャネル名="Webカタログ" プロダクトID="PP25" プロダクト名="SIMM- 16MB PCMCIAIIｶｰﾄﾞ" 売上="0" インダストリーID="GG119" インダストリー名="転売"/><row チャネルID="CC5" チャネル名="Webカタログ" プロダクトID="PP25" プロダクト名="SIMM- 16MB PCMCIAIIｶｰﾄﾞ" 売上="0" インダストリーID="GG120" インダストリー名="政府"/><row チャネルID="CC5" チャネル名="Webカタログ" プロダクトID="PP25" プロダクト名="SIMM- 16MB PCMCIAIIｶｰﾄﾞ" 売上="0" インダストリーID="GG121" インダストリー名="教育"/><row チャネルID="CC5" チャネル名="Webカタログ" プロダクトID="PP26" プロダクト名="ﾏﾙﾁﾒﾃﾞｨｱ･ｽﾋﾟｰｶ" 売上="0" インダストリーID="GG113" インダストリー名="製造"/><row チャネルID="CC5" チャネル名="Webカタログ" プロダクトID="PP26" プロダクト名="ﾏﾙﾁﾒﾃﾞｨｱ･ｽﾋﾟｰｶ" 売上="0" インダストリーID="GG114" インダストリー名="機械"/><row チャネルID="CC5" チャネル名="Webカタログ" プロダクトID="PP26" プロダクト名="ﾏﾙﾁﾒﾃﾞｨｱ･ｽﾋﾟｰｶ" 売上="0" インダストリーID="GG115" インダストリー名="防衛"/><row チャネルID="CC5" チャネル名="Webカタログ" プロダクトID="PP26" プロダクト名="ﾏﾙﾁﾒﾃﾞｨｱ･ｽﾋﾟｰｶ" 売上="0" インダストリーID="GG116" インダストリー名="コンサルティング"/><row チャネルID="CC5" チャネル名="Webカタログ" プロダクトID="PP26" プロダクト名="ﾏﾙﾁﾒﾃﾞｨｱ･ｽﾋﾟｰｶ" 売上="0" インダストリーID="GG117" インダストリー名="ＳＩ"/><row チャネルID="CC5" チャネル名="Webカタログ" プロダクトID="PP26" プロダクト名="ﾏﾙﾁﾒﾃﾞｨｱ･ｽﾋﾟｰｶ" 売上="0" インダストリーID="GG118" インダストリー名="航空宇宙"/><row チャネルID="CC5" チャネル名="Webカタログ" プロダクトID="PP26" プロダクト名="ﾏﾙﾁﾒﾃﾞｨｱ･ｽﾋﾟｰｶ" 売上="0" インダストリーID="GG119" インダストリー名="転売"/><row チャネルID="CC5" チャネル名="Webカタログ" プロダクトID="PP26" プロダクト名="ﾏﾙﾁﾒﾃﾞｨｱ･ｽﾋﾟｰｶ" 売上="0" インダストリーID="GG120" インダストリー名="政府"/><row チャネルID="CC5" チャネル名="Webカタログ" プロダクトID="PP26" プロダクト名="ﾏﾙﾁﾒﾃﾞｨｱ･ｽﾋﾟｰｶ" 売上="0" インダストリーID="GG121" インダストリー名="教育"/><row チャネルID="CC5" チャネル名="Webカタログ" プロダクトID="PP27" プロダクト名="Unix/Windows 1ﾕｰｻﾞ･ﾊﾟｯｸ" 売上="0" インダストリーID="GG113" インダストリー名="製造"/><row チャネルID="CC5" チャネル名="Webカタログ" プロダクトID="PP27" プロダクト名="Unix/Windows 1ﾕｰｻﾞ･ﾊﾟｯｸ" 売上="0" インダストリーID="GG114" インダストリー名="機械"/><row チャネルID="CC5" チャネル名="Webカタログ" プロダクトID="PP27" プロダクト名="Unix/Windows 1ﾕｰｻﾞ･ﾊﾟｯｸ" 売上="0" インダストリーID="GG115" インダストリー名="防衛"/><row チャネルID="CC5" チャネル名="Webカタログ" プロダクトID="PP27" プロダクト名="Unix/Windows 1ﾕｰｻﾞ･ﾊﾟｯｸ" 売上="0" インダストリーID="GG116" インダストリー名="コンサルティング"/><row チャネルID="CC5" チャネル名="Webカタログ" プロダクトID="PP27" プロダクト名="Unix/Windows 1ﾕｰｻﾞ･ﾊﾟｯｸ" 売上="0" インダストリーID="GG117" インダストリー名="ＳＩ"/><row チャネルID="CC5" チャネル名="Webカタログ" プロダクトID="PP27" プロダクト名="Unix/Windows 1ﾕｰｻﾞ･ﾊﾟｯｸ" 売上="0" インダストリーID="GG118" インダストリー名="航空宇宙"/><row チャネルID="CC5" チャネル名="Webカタログ" プロダクトID="PP27" プロダクト名="Unix/Windows 1ﾕｰｻﾞ･ﾊﾟｯｸ" 売上="0" インダストリーID="GG119" インダストリー名="転売"/><row チャネルID="CC5" チャネル名="Webカタログ" プロダクトID="PP27" プロダクト名="Unix/Windows 1ﾕｰｻﾞ･ﾊﾟｯｸ" 売上="0" インダストリーID="GG120" インダストリー名="政府"/><row チャネルID="CC5" チャネル名="Webカタログ" プロダクトID="PP27" プロダクト名="Unix/Windows 1ﾕｰｻﾞ･ﾊﾟｯｸ" 売上="0" インダストリーID="GG121" インダストリー名="教育"/><row チャネルID="CC5" チャネル名="Webカタログ" プロダクトID="PP28" プロダクト名="Unix/Windows 5ﾕｰｻﾞ･ﾊﾟｯｸ" 売上="0" インダストリーID="GG113" インダストリー名="製造"/><row チャネルID="CC5" チャネル名="Webカタログ" プロダクトID="PP28" プロダクト名="Unix/Windows 5ﾕｰｻﾞ･ﾊﾟｯｸ" 売上="0" インダストリーID="GG114" インダストリー名="機械"/><row チャネルID="CC5" チャネル名="Webカタログ" プロダクトID="PP28" プロダクト名="Unix/Windows 5ﾕｰｻﾞ･ﾊﾟｯｸ" 売上="0" インダストリーID="GG115" インダストリー名="防衛"/><row チャネルID="CC5" チャネル名="Webカタログ" プロダクトID="PP28" プロダクト名="Unix/Windows 5ﾕｰｻﾞ･ﾊﾟｯｸ" 売上="0" インダストリーID="GG116" インダストリー名="コンサルティング"/><row チャネルID="CC5" チャネル名="Webカタログ" プロダクトID="PP28" プロダクト名="Unix/Windows 5ﾕｰｻﾞ･ﾊﾟｯｸ" 売上="0" インダストリーID="GG117" インダストリー名="ＳＩ"/><row チャネルID="CC5" チャネル名="Webカタログ" プロダクトID="PP28" プロダクト名="Unix/Windows 5ﾕｰｻﾞ･ﾊﾟｯｸ" 売上="0" インダストリーID="GG118" インダストリー名="航空宇宙"/><row チャネルID="CC5" チャネル名="Webカタログ" プロダクトID="PP28" プロダクト名="Unix/Windows 5ﾕｰｻﾞ･ﾊﾟｯｸ" 売上="0" インダストリーID="GG119" インダストリー名="転売"/><row チャネルID="CC5" チャネル名="Webカタログ" プロダクトID="PP28" プロダクト名="Unix/Windows 5ﾕｰｻﾞ･ﾊﾟｯｸ" 売上="0" インダストリーID="GG120" インダストリー名="政府"/><row チャネルID="CC5" チャネル名="Webカタログ" プロダクトID="PP28" プロダクト名="Unix/Windows 5ﾕｰｻﾞ･ﾊﾟｯｸ" 売上="0" インダストリーID="GG121" インダストリー名="教育"/><row チャネルID="CC5" チャネル名="Webカタログ" プロダクトID="PP29" プロダクト名="マウス・パッド" 売上="0" インダストリーID="GG113" インダストリー名="製造"/><row チャネルID="CC5" チャネル名="Webカタログ" プロダクトID="PP29" プロダクト名="マウス・パッド" 売上="0" インダストリーID="GG114" インダストリー名="機械"/><row チャネルID="CC5" チャネル名="Webカタログ" プロダクトID="PP29" プロダクト名="マウス・パッド" 売上="0" インダストリーID="GG115" インダストリー名="防衛"/><row チャネルID="CC5" チャネル名="Webカタログ" プロダクトID="PP29" プロダクト名="マウス・パッド" 売上="0" インダストリーID="GG116" インダストリー名="コンサルティング"/><row チャネルID="CC5" チャネル名="Webカタログ" プロダクトID="PP29" プロダクト名="マウス・パッド" 売上="0" インダストリーID="GG117" インダストリー名="ＳＩ"/><row チャネルID="CC5" チャネル名="Webカタログ" プロダクトID="PP29" プロダクト名="マウス・パッド" 売上="0" インダストリーID="GG118" インダストリー名="航空宇宙"/><row チャネルID="CC5" チャネル名="Webカタログ" プロダクトID="PP29" プロダクト名="マウス・パッド" 売上="0" インダストリーID="GG119" インダストリー名="転売"/><row チャネルID="CC5" チャネル名="Webカタログ" プロダクトID="PP29" プロダクト名="マウス・パッド" 売上="0" インダストリーID="GG120" インダストリー名="政府"/><row チャネルID="CC5" チャネル名="Webカタログ" プロダクトID="PP29" プロダクト名="マウス・パッド" 売上="0" インダストリーID="GG121" インダストリー名="教育"/><row チャネルID="CC5" チャネル名="Webカタログ" プロダクトID="PP30" プロダクト名="2.88MB  3.5 FD" 売上="0" インダストリーID="GG113" インダストリー名="製造"/><row チャネルID="CC5" チャネル名="Webカタログ" プロダクトID="PP30" プロダクト名="2.88MB  3.5 FD" 売上="0" インダストリーID="GG114" インダストリー名="機械"/><row チャネルID="CC5" チャネル名="Webカタログ" プロダクトID="PP30" プロダクト名="2.88MB  3.5 FD" 売上="0" インダストリーID="GG115" インダストリー名="防衛"/><row チャネルID="CC5" チャネル名="Webカタログ" プロダクトID="PP30" プロダクト名="2.88MB  3.5 FD" 売上="0" インダストリーID="GG116" インダストリー名="コンサルティング"/><row チャネルID="CC5" チャネル名="Webカタログ" プロダクトID="PP30" プロダクト名="2.88MB  3.5 FD" 売上="0" インダストリーID="GG117" インダストリー名="ＳＩ"/><row チャネルID="CC5" チャネル名="Webカタログ" プロダクトID="PP30" プロダクト名="2.88MB  3.5 FD" 売上="0" インダストリーID="GG118" インダストリー名="航空宇宙"/><row チャネルID="CC5" チャネル名="Webカタログ" プロダクトID="PP30" プロダクト名="2.88MB  3.5 FD" 売上="0" インダストリーID="GG119" インダストリー名="転売"/><row チャネルID="CC5" チャネル名="Webカタログ" プロダクトID="PP30" プロダクト名="2.88MB  3.5 FD" 売上="0" インダストリーID="GG120" インダストリー名="政府"/><row チャネルID="CC5" チャネル名="Webカタログ" プロダクトID="PP30" プロダクト名="2.88MB  3.5 FD" 売上="0" インダストリーID="GG121" インダストリー名="教育"/><row チャネルID="CC5" チャネル名="Webカタログ" プロダクトID="PP31" プロダクト名="ﾏﾙﾁﾒﾃﾞｨｱ･ｽﾋﾟｰｶ" 売上="0" インダストリーID="GG113" インダストリー名="製造"/><row チャネルID="CC5" チャネル名="Webカタログ" プロダクトID="PP31" プロダクト名="ﾏﾙﾁﾒﾃﾞｨｱ･ｽﾋﾟｰｶ" 売上="0" インダストリーID="GG114" インダストリー名="機械"/><row チャネルID="CC5" チャネル名="Webカタログ" プロダクトID="PP31" プロダクト名="ﾏﾙﾁﾒﾃﾞｨｱ･ｽﾋﾟｰｶ" 売上="0" インダストリーID="GG115" インダストリー名="防衛"/><row チャネルID="CC5" チャネル名="Webカタログ" プロダクトID="PP31" プロダクト名="ﾏﾙﾁﾒﾃﾞｨｱ･ｽﾋﾟｰｶ" 売上="0" インダストリーID="GG116" インダストリー名="コンサルティング"/><row チャネルID="CC5" チャネル名="Webカタログ" プロダクトID="PP31" プロダクト名="ﾏﾙﾁﾒﾃﾞｨｱ･ｽﾋﾟｰｶ" 売上="0" インダストリーID="GG117" インダストリー名="ＳＩ"/><row チャネルID="CC5" チャネル名="Webカタログ" プロダクトID="PP31" プロダクト名="ﾏﾙﾁﾒﾃﾞｨｱ･ｽﾋﾟｰｶ" 売上="0" インダストリーID="GG118" インダストリー名="航空宇宙"/><row チャネルID="CC5" チャネル名="Webカタログ" プロダクトID="PP31" プロダクト名="ﾏﾙﾁﾒﾃﾞｨｱ･ｽﾋﾟｰｶ" 売上="0" インダストリーID="GG119" インダストリー名="転売"/><row チャネルID="CC5" チャネル名="Webカタログ" プロダクトID="PP31" プロダクト名="ﾏﾙﾁﾒﾃﾞｨｱ･ｽﾋﾟｰｶ" 売上="0" インダストリーID="GG120" インダストリー名="政府"/><row チャネルID="CC5" チャネル名="Webカタログ" プロダクトID="PP31" プロダクト名="ﾏﾙﾁﾒﾃﾞｨｱ･ｽﾋﾟｰｶ" 売上="0" インダストリーID="GG121" インダストリー名="教育"/><row チャネルID="CC5" チャネル名="Webカタログ" プロダクトID="PP32" プロダクト名="PCMCIA ﾓﾃﾞﾑ/FAX 19200bps" 売上="0" インダストリーID="GG113" インダストリー名="製造"/><row チャネルID="CC5" チャネル名="Webカタログ" プロダクトID="PP32" プロダクト名="PCMCIA ﾓﾃﾞﾑ/FAX 19200bps" 売上="0" インダストリーID="GG114" インダストリー名="機械"/><row チャネルID="CC5" チャネル名="Webカタログ" プロダクトID="PP32" プロダクト名="PCMCIA ﾓﾃﾞﾑ/FAX 19200bps" 売上="0" インダストリーID="GG115" インダストリー名="防衛"/><row チャネルID="CC5" チャネル名="Webカタログ" プロダクトID="PP32" プロダクト名="PCMCIA ﾓﾃﾞﾑ/FAX 19200bps" 売上="0" インダストリーID="GG116" インダストリー名="コンサルティング"/><row チャネルID="CC5" チャネル名="Webカタログ" プロダクトID="PP32" プロダクト名="PCMCIA ﾓﾃﾞﾑ/FAX 19200bps" 売上="0" インダストリーID="GG117" インダストリー名="ＳＩ"/><row チャネルID="CC5" チャネル名="Webカタログ" プロダクトID="PP32" プロダクト名="PCMCIA ﾓﾃﾞﾑ/FAX 19200bps" 売上="0" インダストリーID="GG118" インダストリー名="航空宇宙"/><row チャネルID="CC5" チャネル名="Webカタログ" プロダクトID="PP32" プロダクト名="PCMCIA ﾓﾃﾞﾑ/FAX 19200bps" 売上="0" インダストリーID="GG119" インダストリー名="転売"/><row チャネルID="CC5" チャネル名="Webカタログ" プロダクトID="PP32" プロダクト名="PCMCIA ﾓﾃﾞﾑ/FAX 19200bps" 売上="0" インダストリーID="GG120" インダストリー名="政府"/><row チャネルID="CC5" チャネル名="Webカタログ" プロダクトID="PP32" プロダクト名="PCMCIA ﾓﾃﾞﾑ/FAX 19200bps" 売上="0" インダストリーID="GG121" インダストリー名="教育"/></data></OpenOLAP>
